GP01/sum_accumulator/rtl/sum_accumulator.sv
module sum_accumulator#(
    // * -------------------------------------------------
    // * Parameters
    // * -------------------------------------------------
    parameter                            NB_DATA_IN  = 3 ,
    parameter                            NB_SEL      = 2 ,
    parameter                            NB_DATA_OUT = 6
)
(
    // * -------------------------------------------------
    // * Outputs
    // * -------------------------------------------------
    output logic [ NB_DATA_OUT - 1 : 0 ] o_data          ,
    output logic                         o_overflow      ,

    // * -------------------------------------------------
    // * Inputs
    // * -------------------------------------------------
    input  logic [ NB_DATA_IN  - 1 : 0 ] i_data1         ,
    input  logic [ NB_DATA_IN  - 1 : 0 ] i_data2         ,
    input  logic [ NB_SEL      - 1 : 0 ] i_sel           ,

    // * -------------------------------------------------
    // * Clock and reset
    // * -------------------------------------------------
    input  logic                         i_rst_n         ,
    input  logic                         i_clk
) ;

    // * -------------------------------------------------
    // * Internal logics
    // * -------------------------------------------------
    logic        [ NB_DATA_IN      : 0 ] expanded_data1  ;
    logic        [ NB_DATA_IN      : 0 ] expanded_data2  ;
    logic        [ NB_DATA_IN      : 0 ] in_data_sum     ;
    logic        [ NB_DATA_IN      : 0 ] data_sel        ;
    logic        [ NB_DATA_OUT     : 0 ] sum             ;
    logic        [ NB_DATA_OUT - 1 : 0 ] sum_d           ;
    logic                                overflow        ;

    // * -------------------------------------------------
    // * Expansion and sum
    // * -------------------------------------------------
    assign expanded_data1 = {1'b0, i_data1}                 ;
    assign expanded_data2 = {1'b0, i_data2}                 ;
    assign in_data_sum    = expanded_data1 + expanded_data2 ;

    // * -------------------------------------------------
    // * Data selection
    // * -------------------------------------------------
    typedef enum logic [NB_SEL-1:0] {
        SELECT_DATA_1   = 2'b10 ,
        SELECT_DATA_2   = 2'b00 ,
        SELECT_DATA_SUM = 2'b01
    } selector_e;

    always_comb
    begin : proc_muxing
        unique case (i_sel)
            SELECT_DATA_1   : data_sel = expanded_data1 ;
            SELECT_DATA_2   : data_sel = expanded_data2 ;
            SELECT_DATA_SUM : data_sel = in_data_sum    ;
        endcase
    end

    // * -------------------------------------------------
    // * Accumulation
    // * -------------------------------------------------
    assign sum = {1'b0, sum_d} + {{NB_DATA_OUT-NB_DATA_IN{1'b0}}, data_sel};

    always_ff @(posedge i_clk or negedge i_rst_n)
    begin : proc_accum
        if (~i_rst_n) begin
            sum_d    <= '0               ;
            overflow <= '0               ;
        end else begin
            sum_d    <= sum              ;
            overflow <= sum[NB_DATA_OUT] ;
        end
    end

    // * -------------------------------------------------
    // * Output assignment
    // * -------------------------------------------------
    assign o_data     = sum_d [ NB_DATA_OUT - 1 : 0 ] ;
    assign o_overflow = overflow                      ;

    // * -------------------------------------------------
    // * Simulation define
    // * -------------------------------------------------
    `ifdef COCOTB_SIM
        initial begin
            $dumpfile ("dump.vcd");
            $dumpvars ();
            #1;
        end
    `endif
endmodule

GP01/sum_accumulator/tb/dump.vcd
$date
	Mon Sep 16 23:26:26 2024
$end
$version
	Icarus Verilog
$end
$timescale
	1ps
$end
$scope module sum_accumulator $end
$var wire 1 ! i_clk $end
$var wire 3 " i_data1 [2:0] $end
$var wire 3 # i_data2 [2:0] $end
$var wire 1 $ i_rst_n $end
$var wire 2 % i_sel [1:0] $end
$var wire 6 & o_data [5:0] $end
$var wire 1 ' o_overflow $end
$var wire 7 ( sum [6:0] $end
$var wire 4 ) in_data_sum [3:0] $end
$var wire 4 * expanded_data2 [3:0] $end
$var wire 4 + expanded_data1 [3:0] $end
$var parameter 32 , NB_DATA_IN $end
$var parameter 32 - NB_DATA_OUT $end
$var parameter 32 . NB_SEL $end
$var reg 4 / data_sel [3:0] $end
$var reg 1 0 overflow $end
$var reg 6 1 sum_d [5:0] $end
$scope begin proc_accum $end
$upscope $end
$scope begin proc_muxing $end
$upscope $end
$upscope $end
$enddefinitions $end
$comment Show the parameter values. $end
$dumpall
b10 .
b110 -
b11 ,
$end
#0
$dumpvars
bx 1
x0
b0 /
b0 +
b0 *
b0 )
bx (
x'
bx &
b0 %
1$
b0 #
b0 "
1!
$end
#5000
0!
#10000
0'
00
b0 (
b0 &
b0 1
1!
0$
#15000
0!
#20000
1!
#25000
0!
#30000
1!
#35000
0!
#40000
1!
#45000
b1 (
b1 /
0!
b10 %
b10 *
b10 #
b11 )
b1 +
b1 "
1$
#50000
b10 (
b1 &
b1 1
1!
#55000
0!
#60000
b11 (
b10 &
b10 1
1!
#65000
0!
#70000
b100 (
b11 &
b11 1
1!
#75000
0!
#80000
b101 (
b100 &
b100 1
1!
#85000
0!
#90000
b110 (
b101 &
b101 1
1!
#95000
0!
#100000
b111 (
b110 &
b110 1
1!
#105000
0!
#110000
b1000 (
b111 &
b111 1
1!
#115000
0!
#120000
b1001 (
b1000 &
b1000 1
1!
#125000
0!
#130000
b1010 (
b1001 &
b1001 1
1!
#135000
0!
#140000
b1011 (
b1010 &
b1010 1
1!
#145000
0!
#150000
b1100 (
b1011 &
b1011 1
1!
#155000
0!
#160000
b1101 (
b1100 &
b1100 1
1!
#165000
0!
#170000
b1110 (
b1101 &
b1101 1
1!
#175000
0!
#180000
b1111 (
b1110 &
b1110 1
1!
#185000
0!
#190000
b10000 (
b1111 &
b1111 1
1!
#195000
0!
#200000
b10001 (
b10000 &
b10000 1
1!
#205000
0!
#210000
b10010 (
b10001 &
b10001 1
1!
#215000
0!
#220000
b10011 (
b10010 &
b10010 1
1!
#225000
0!
#230000
b10100 (
b10011 &
b10011 1
1!
#235000
0!
#240000
b10101 (
b10100 &
b10100 1
1!
#245000
0!
#250000
b10110 (
b10101 &
b10101 1
1!
#255000
0!
#260000
b10111 (
b10110 &
b10110 1
1!
#265000
0!
#270000
b11000 (
b10111 &
b10111 1
1!
#275000
0!
#280000
b11001 (
b11000 &
b11000 1
1!
#285000
0!
#290000
b11010 (
b11001 &
b11001 1
1!
#295000
0!
#300000
b11011 (
b11010 &
b11010 1
1!
#305000
0!
#310000
b11100 (
b11011 &
b11011 1
1!
#315000
0!
#320000
b11101 (
b11100 &
b11100 1
1!
#325000
0!
#330000
b11110 (
b11101 &
b11101 1
1!
#335000
0!
#340000
b11111 (
b11110 &
b11110 1
1!
#345000
0!
#350000
b100000 (
b11111 &
b11111 1
1!
#355000
0!
#360000
b100001 (
b100000 &
b100000 1
1!
#365000
0!
#370000
b100010 (
b100001 &
b100001 1
1!
#375000
0!
#380000
b100011 (
b100010 &
b100010 1
1!
#385000
0!
#390000
b100100 (
b100011 &
b100011 1
1!
#395000
0!
#400000
b100101 (
b100100 &
b100100 1
1!
#405000
0!
#410000
b100110 (
b100101 &
b100101 1
1!
#415000
0!
#420000
b100111 (
b100110 &
b100110 1
1!
#425000
0!
#430000
b101000 (
b100111 &
b100111 1
1!
#435000
0!
#440000
b101001 (
b101000 &
b101000 1
1!
#445000
0!
#450000
b101010 (
b101001 &
b101001 1
1!
#455000
0!
#460000
b101011 (
b101010 &
b101010 1
1!
#465000
0!
#470000
b101100 (
b101011 &
b101011 1
1!
#475000
0!
#480000
b101101 (
b101100 &
b101100 1
1!
#485000
0!
#490000
b101110 (
b101101 &
b101101 1
1!
#495000
0!
#500000
b101111 (
b101110 &
b101110 1
1!
#505000
0!
#510000
b110000 (
b101111 &
b101111 1
1!
#515000
0!
#520000
b110001 (
b110000 &
b110000 1
1!
#525000
0!
#530000
b110010 (
b110001 &
b110001 1
1!
#535000
0!
#540000
b110011 (
b110010 &
b110010 1
1!
#545000
0!
#550000
b110100 (
b110011 &
b110011 1
1!
#555000
0!
#560000
b110101 (
b110100 &
b110100 1
1!
#565000
0!
#570000
b110110 (
b110101 &
b110101 1
1!
#575000
0!
#580000
b110111 (
b110110 &
b110110 1
1!
#585000
0!
#590000
b111000 (
b110111 &
b110111 1
1!
#595000
0!
#600000
b111001 (
b111000 &
b111000 1
1!
#605000
0!
#610000
b111010 (
b111001 &
b111001 1
1!
#615000
0!
#620000
b111011 (
b111010 &
b111010 1
1!
#625000
0!
#630000
b111100 (
b111011 &
b111011 1
1!
#635000
0!
#640000
b111101 (
b111100 &
b111100 1
1!
#645000
0!
#650000
b111110 (
b111101 &
b111101 1
1!
#655000
0!
#660000
b111111 (
b111110 &
b111110 1
1!
#665000
0!
#670000
b1000000 (
b111111 &
b111111 1
1!
#675000
0!
#680000
1'
10
b1 (
b0 &
b0 1
1!
#685000
0!
#690000
0'
00
b10 (
b1 &
b1 1
1!
#695000
0!
#700000
b11 (
b10 &
b10 1
1!
#705000
0!
#710000
b100 (
b11 &
b11 1
1!
#715000
0!
#720000
b101 (
b100 &
b100 1
1!
#725000
0!
#730000
b110 (
b101 &
b101 1
1!
#735000
0!
#740000
b111 (
b110 &
b110 1
1!
#745000
0!
#750000
b1000 (
b111 &
b111 1
1!
#755000
0!
#760000
b1001 (
b1000 &
b1000 1
1!
#765000
0!
#770000
b1010 (
b1001 &
b1001 1
1!
#775000
0!
#780000
b1011 (
b1010 &
b1010 1
1!
#785000
0!
#790000
b1100 (
b1011 &
b1011 1
1!
#795000
0!
#800000
b1101 (
b1100 &
b1100 1
1!
#805000
0!
#810000
b1110 (
b1101 &
b1101 1
1!
#815000
0!
#820000
b1111 (
b1110 &
b1110 1
1!
#825000
0!
#830000
b10000 (
b1111 &
b1111 1
1!
#835000
0!
#840000
b10001 (
b10000 &
b10000 1
1!
#845000
0!
#850000
b10010 (
b10001 &
b10001 1
1!
#855000
0!
#860000
b10011 (
b10010 &
b10010 1
1!
#865000
0!
#870000
b10100 (
b10011 &
b10011 1
1!
#875000
0!
#880000
b10101 (
b10100 &
b10100 1
1!
#885000
0!
#890000
b10110 (
b10101 &
b10101 1
1!
#895000
0!
#900000
b10111 (
b10110 &
b10110 1
1!
#905000
0!
#910000
b11000 (
b10111 &
b10111 1
1!
#915000
0!
#920000
b11001 (
b11000 &
b11000 1
1!
#925000
0!
#930000
b11010 (
b11001 &
b11001 1
1!
#935000
0!
#940000
b11011 (
b11010 &
b11010 1
1!
#945000
0!
#950000
b11100 (
b11011 &
b11011 1
1!
#955000
0!
#960000
b11101 (
b11100 &
b11100 1
1!
#965000
0!
#970000
b11110 (
b11101 &
b11101 1
1!
#975000
0!
#980000
b11111 (
b11110 &
b11110 1
1!
#985000
0!
#990000
b100000 (
b11111 &
b11111 1
1!
#995000
0!
#1000000
b100001 (
b100000 &
b100000 1
1!
#1005000
0!
#1010000
b100010 (
b100001 &
b100001 1
1!
#1015000
0!
#1020000
b100011 (
b100010 &
b100010 1
1!
#1025000
0!
#1030000
b100100 (
b100011 &
b100011 1
1!
#1035000
0!
#1040000
b100101 (
b100100 &
b100100 1
1!
#1045000
0!
#1050000
b100110 (
b100101 &
b100101 1
1!
#1055000
0!
#1060000
b100111 (
b100110 &
b100110 1
1!
#1065000
0!
#1070000
b101000 (
b100111 &
b100111 1
1!
#1075000
0!
#1080000
b101001 (
b101000 &
b101000 1
1!
#1085000
0!
#1090000
b101010 (
b101001 &
b101001 1
1!
#1095000
0!
#1100000
b101011 (
b101010 &
b101010 1
1!
#1105000
0!
#1110000
b101100 (
b101011 &
b101011 1
1!
#1115000
0!
#1120000
b101101 (
b101100 &
b101100 1
1!
#1125000
0!
#1130000
b101110 (
b101101 &
b101101 1
1!
#1135000
0!
#1140000
b101111 (
b101110 &
b101110 1
1!
#1145000
0!
#1150000
b110000 (
b101111 &
b101111 1
1!
#1155000
0!
#1160000
b110001 (
b110000 &
b110000 1
1!
#1165000
0!
#1170000
b110010 (
b110001 &
b110001 1
1!
#1175000
0!
#1180000
b110011 (
b110010 &
b110010 1
1!
#1185000
0!
#1190000
b110100 (
b110011 &
b110011 1
1!
#1195000
0!
#1200000
b110101 (
b110100 &
b110100 1
1!
#1205000
0!
#1210000
b110110 (
b110101 &
b110101 1
1!
#1215000
0!
#1220000
b110111 (
b110110 &
b110110 1
1!
#1225000
0!
#1230000
b111000 (
b110111 &
b110111 1
1!
#1235000
0!
#1240000
b111001 (
b111000 &
b111000 1
1!
#1245000
0!
#1250000
b111010 (
b111001 &
b111001 1
1!
#1255000
0!
#1260000
b111011 (
b111010 &
b111010 1
1!
#1265000
0!
#1270000
b111100 (
b111011 &
b111011 1
1!
#1275000
0!
#1280000
b111101 (
b111100 &
b111100 1
1!
#1285000
0!
#1290000
b111110 (
b111101 &
b111101 1
1!
#1295000
0!
#1300000
b111111 (
b111110 &
b111110 1
1!
#1305000
0!
#1310000
b1000000 (
b111111 &
b111111 1
1!
#1315000
0!
#1320000
1'
10
b1 (
b0 &
b0 1
1!
#1325000
0!
#1330000
0'
00
b10 (
b1 &
b1 1
1!
#1335000
0!
#1340000
b11 (
b10 &
b10 1
1!
#1345000
0!
#1350000
b100 (
b11 &
b11 1
1!
#1355000
0!
#1360000
b101 (
b100 &
b100 1
1!
#1365000
0!
#1370000
b110 (
b101 &
b101 1
1!
#1375000
0!
#1380000
b111 (
b110 &
b110 1
1!
#1385000
0!
#1390000
b1000 (
b111 &
b111 1
1!
#1395000
0!
#1400000
b1001 (
b1000 &
b1000 1
1!
#1405000
0!
#1410000
b1010 (
b1001 &
b1001 1
1!
#1415000
0!
#1420000
b1011 (
b1010 &
b1010 1
1!
#1425000
0!
#1430000
b1100 (
b1011 &
b1011 1
1!
#1435000
0!
#1440000
b1101 (
b1100 &
b1100 1
1!
#1445000
0!
#1450000
b1110 (
b1101 &
b1101 1
1!
#1455000
0!
#1460000
b1111 (
b1110 &
b1110 1
1!
#1465000
0!
#1470000
b10000 (
b1111 &
b1111 1
1!
#1475000
0!
#1480000
b10001 (
b10000 &
b10000 1
1!
#1485000
0!
#1490000
b10010 (
b10001 &
b10001 1
1!
#1495000
0!
#1500000
b10011 (
b10010 &
b10010 1
1!
#1505000
0!
#1510000
b10100 (
b10011 &
b10011 1
1!
#1515000
0!
#1520000
b10101 (
b10100 &
b10100 1
1!
#1525000
0!
#1530000
b10110 (
b10101 &
b10101 1
1!
#1535000
0!
#1540000
b10111 (
b10110 &
b10110 1
1!
#1545000
0!
#1550000
b11000 (
b10111 &
b10111 1
1!
#1555000
0!
#1560000
b11001 (
b11000 &
b11000 1
1!
#1565000
0!
#1570000
b11010 (
b11001 &
b11001 1
1!
#1575000
0!
#1580000
b11011 (
b11010 &
b11010 1
1!
#1585000
0!
#1590000
b11100 (
b11011 &
b11011 1
1!
#1595000
0!
#1600000
b11101 (
b11100 &
b11100 1
1!
#1605000
0!
#1610000
b11110 (
b11101 &
b11101 1
1!
#1615000
0!
#1620000
b11111 (
b11110 &
b11110 1
1!
#1625000
0!
#1630000
b100000 (
b11111 &
b11111 1
1!
#1635000
0!
#1640000
b100001 (
b100000 &
b100000 1
1!
#1645000
0!
#1650000
b100010 (
b100001 &
b100001 1
1!
#1655000
0!
#1660000
b100011 (
b100010 &
b100010 1
1!
#1665000
0!
#1670000
b100100 (
b100011 &
b100011 1
1!
#1675000
0!
#1680000
b100101 (
b100100 &
b100100 1
1!
#1685000
0!
#1690000
b100110 (
b100101 &
b100101 1
1!
#1695000
0!
#1700000
b100111 (
b100110 &
b100110 1
1!
#1705000
0!
#1710000
b101000 (
b100111 &
b100111 1
1!
#1715000
0!
#1720000
b101001 (
b101000 &
b101000 1
1!
#1725000
0!
#1730000
b101010 (
b101001 &
b101001 1
1!
#1735000
0!
#1740000
b101011 (
b101010 &
b101010 1
1!
#1745000
0!
#1750000
b101100 (
b101011 &
b101011 1
1!
#1755000
0!
#1760000
b101101 (
b101100 &
b101100 1
1!
#1765000
0!
#1770000
b101110 (
b101101 &
b101101 1
1!
#1775000
0!
#1780000
b101111 (
b101110 &
b101110 1
1!
#1785000
0!
#1790000
b110000 (
b101111 &
b101111 1
1!
#1795000
0!
#1800000
b110001 (
b110000 &
b110000 1
1!
#1805000
0!
#1810000
b110010 (
b110001 &
b110001 1
1!
#1815000
0!
#1820000
b110011 (
b110010 &
b110010 1
1!
#1825000
0!
#1830000
b110100 (
b110011 &
b110011 1
1!
#1835000
0!
#1840000
b110101 (
b110100 &
b110100 1
1!
#1845000
0!
#1850000
b110110 (
b110101 &
b110101 1
1!
#1855000
0!
#1860000
b110111 (
b110110 &
b110110 1
1!
#1865000
0!
#1870000
b111000 (
b110111 &
b110111 1
1!
#1875000
0!
#1880000
b111001 (
b111000 &
b111000 1
1!
#1885000
0!
#1890000
b111010 (
b111001 &
b111001 1
1!
#1895000
0!
#1900000
b111011 (
b111010 &
b111010 1
1!
#1905000
0!
#1910000
b111100 (
b111011 &
b111011 1
1!
#1915000
0!
#1920000
b111101 (
b111100 &
b111100 1
1!
#1925000
0!
#1930000
b111110 (
b111101 &
b111101 1
1!
#1935000
0!
#1940000
b111111 (
b111110 &
b111110 1
1!
#1945000
0!
#1950000
b1000000 (
b111111 &
b111111 1
1!
#1955000
0!
#1960000
1'
10
b1 (
b0 &
b0 1
1!
#1965000
0!
#1970000
0'
00
b10 (
b1 &
b1 1
1!
#1975000
0!
#1980000
b11 (
b10 &
b10 1
1!
#1985000
0!
#1990000
b100 (
b11 &
b11 1
1!
#1995000
0!
#2000000
b101 (
b100 &
b100 1
1!
#2005000
0!
#2010000
b110 (
b101 &
b101 1
1!
#2015000
0!
#2020000
b111 (
b110 &
b110 1
1!
#2025000
0!
#2030000
b1000 (
b111 &
b111 1
1!
#2035000
0!
#2040000
b1001 (
b1000 &
b1000 1
1!
#2040001
b1000 (
b0 /
b0 %
b0 *
b0 #
b0 )
b0 +
b0 "
#2045001
0!
#2050001
b0 (
b0 &
b0 1
1!
0$
#2055001
0!
#2060001
1!
#2065001
0!
#2070001
1!
#2075001
0!
#2080001
1!
#2085001
b10 (
b10 /
0!
b10 *
b10 #
b11 )
b1 +
b1 "
1$
#2090001
b100 (
b10 &
b10 1
1!
#2095001
0!
#2100001
b110 (
b100 &
b100 1
1!
#2105001
0!
#2110001
b1000 (
b110 &
b110 1
1!
#2115001
0!
#2120001
b1010 (
b1000 &
b1000 1
1!
#2125001
0!
#2130001
b1100 (
b1010 &
b1010 1
1!
#2135001
0!
#2140001
b1110 (
b1100 &
b1100 1
1!
#2145001
0!
#2150001
b10000 (
b1110 &
b1110 1
1!
#2155001
0!
#2160001
b10010 (
b10000 &
b10000 1
1!
#2165001
0!
#2170001
b10100 (
b10010 &
b10010 1
1!
#2175001
0!
#2180001
b10110 (
b10100 &
b10100 1
1!
#2185001
0!
#2190001
b11000 (
b10110 &
b10110 1
1!
#2195001
0!
#2200001
b11010 (
b11000 &
b11000 1
1!
#2205001
0!
#2210001
b11100 (
b11010 &
b11010 1
1!
#2215001
0!
#2220001
b11110 (
b11100 &
b11100 1
1!
#2225001
0!
#2230001
b100000 (
b11110 &
b11110 1
1!
#2235001
0!
#2240001
b100010 (
b100000 &
b100000 1
1!
#2245001
0!
#2250001
b100100 (
b100010 &
b100010 1
1!
#2255001
0!
#2260001
b100110 (
b100100 &
b100100 1
1!
#2265001
0!
#2270001
b101000 (
b100110 &
b100110 1
1!
#2275001
0!
#2280001
b101010 (
b101000 &
b101000 1
1!
#2285001
0!
#2290001
b101100 (
b101010 &
b101010 1
1!
#2295001
0!
#2300001
b101110 (
b101100 &
b101100 1
1!
#2305001
0!
#2310001
b110000 (
b101110 &
b101110 1
1!
#2315001
0!
#2320001
b110010 (
b110000 &
b110000 1
1!
#2325001
0!
#2330001
b110100 (
b110010 &
b110010 1
1!
#2335001
0!
#2340001
b110110 (
b110100 &
b110100 1
1!
#2345001
0!
#2350001
b111000 (
b110110 &
b110110 1
1!
#2355001
0!
#2360001
b111010 (
b111000 &
b111000 1
1!
#2365001
0!
#2370001
b111100 (
b111010 &
b111010 1
1!
#2375001
0!
#2380001
b111110 (
b111100 &
b111100 1
1!
#2385001
0!
#2390001
b1000000 (
b111110 &
b111110 1
1!
#2395001
0!
#2400001
1'
10
b10 (
b0 &
b0 1
1!
#2405001
0!
#2410001
0'
00
b100 (
b10 &
b10 1
1!
#2415001
0!
#2420001
b110 (
b100 &
b100 1
1!
#2425001
0!
#2430001
b1000 (
b110 &
b110 1
1!
#2435001
0!
#2440001
b1010 (
b1000 &
b1000 1
1!
#2445001
0!
#2450001
b1100 (
b1010 &
b1010 1
1!
#2455001
0!
#2460001
b1110 (
b1100 &
b1100 1
1!
#2465001
0!
#2470001
b10000 (
b1110 &
b1110 1
1!
#2475001
0!
#2480001
b10010 (
b10000 &
b10000 1
1!
#2485001
0!
#2490001
b10100 (
b10010 &
b10010 1
1!
#2495001
0!
#2500001
b10110 (
b10100 &
b10100 1
1!
#2505001
0!
#2510001
b11000 (
b10110 &
b10110 1
1!
#2515001
0!
#2520001
b11010 (
b11000 &
b11000 1
1!
#2525001
0!
#2530001
b11100 (
b11010 &
b11010 1
1!
#2535001
0!
#2540001
b11110 (
b11100 &
b11100 1
1!
#2545001
0!
#2550001
b100000 (
b11110 &
b11110 1
1!
#2555001
0!
#2560001
b100010 (
b100000 &
b100000 1
1!
#2565001
0!
#2570001
b100100 (
b100010 &
b100010 1
1!
#2575001
0!
#2580001
b100110 (
b100100 &
b100100 1
1!
#2585001
0!
#2590001
b101000 (
b100110 &
b100110 1
1!
#2595001
0!
#2600001
b101010 (
b101000 &
b101000 1
1!
#2605001
0!
#2610001
b101100 (
b101010 &
b101010 1
1!
#2615001
0!
#2620001
b101110 (
b101100 &
b101100 1
1!
#2625001
0!
#2630001
b110000 (
b101110 &
b101110 1
1!
#2635001
0!
#2640001
b110010 (
b110000 &
b110000 1
1!
#2645001
0!
#2650001
b110100 (
b110010 &
b110010 1
1!
#2655001
0!
#2660001
b110110 (
b110100 &
b110100 1
1!
#2665001
0!
#2670001
b111000 (
b110110 &
b110110 1
1!
#2675001
0!
#2680001
b111010 (
b111000 &
b111000 1
1!
#2685001
0!
#2690001
b111100 (
b111010 &
b111010 1
1!
#2695001
0!
#2700001
b111110 (
b111100 &
b111100 1
1!
#2705001
0!
#2710001
b1000000 (
b111110 &
b111110 1
1!
#2715001
0!
#2720001
1'
10
b10 (
b0 &
b0 1
1!
#2725001
0!
#2730001
0'
00
b100 (
b10 &
b10 1
1!
#2735001
0!
#2740001
b110 (
b100 &
b100 1
1!
#2745001
0!
#2750001
b1000 (
b110 &
b110 1
1!
#2755001
0!
#2760001
b1010 (
b1000 &
b1000 1
1!
#2765001
0!
#2770001
b1100 (
b1010 &
b1010 1
1!
#2775001
0!
#2780001
b1110 (
b1100 &
b1100 1
1!
#2785001
0!
#2790001
b10000 (
b1110 &
b1110 1
1!
#2795001
0!
#2800001
b10010 (
b10000 &
b10000 1
1!
#2805001
0!
#2810001
b10100 (
b10010 &
b10010 1
1!
#2815001
0!
#2820001
b10110 (
b10100 &
b10100 1
1!
#2825001
0!
#2830001
b11000 (
b10110 &
b10110 1
1!
#2835001
0!
#2840001
b11010 (
b11000 &
b11000 1
1!
#2845001
0!
#2850001
b11100 (
b11010 &
b11010 1
1!
#2855001
0!
#2860001
b11110 (
b11100 &
b11100 1
1!
#2865001
0!
#2870001
b100000 (
b11110 &
b11110 1
1!
#2875001
0!
#2880001
b100010 (
b100000 &
b100000 1
1!
#2885001
0!
#2890001
b100100 (
b100010 &
b100010 1
1!
#2895001
0!
#2900001
b100110 (
b100100 &
b100100 1
1!
#2905001
0!
#2910001
b101000 (
b100110 &
b100110 1
1!
#2915001
0!
#2920001
b101010 (
b101000 &
b101000 1
1!
#2925001
0!
#2930001
b101100 (
b101010 &
b101010 1
1!
#2935001
0!
#2940001
b101110 (
b101100 &
b101100 1
1!
#2945001
0!
#2950001
b110000 (
b101110 &
b101110 1
1!
#2955001
0!
#2960001
b110010 (
b110000 &
b110000 1
1!
#2965001
0!
#2970001
b110100 (
b110010 &
b110010 1
1!
#2975001
0!
#2980001
b110110 (
b110100 &
b110100 1
1!
#2985001
0!
#2990001
b111000 (
b110110 &
b110110 1
1!
#2995001
0!
#3000001
b111010 (
b111000 &
b111000 1
1!
#3005001
0!
#3010001
b111100 (
b111010 &
b111010 1
1!
#3015001
0!
#3020001
b111110 (
b111100 &
b111100 1
1!
#3025001
0!
#3030001
b1000000 (
b111110 &
b111110 1
1!
#3035001
0!
#3040001
1'
10
b10 (
b0 &
b0 1
1!
#3045001
0!
#3050001
0'
00
b100 (
b10 &
b10 1
1!
#3055001
0!
#3060001
b110 (
b100 &
b100 1
1!
#3065001
0!
#3070001
b1000 (
b110 &
b110 1
1!
#3075001
0!
#3080001
b1010 (
b1000 &
b1000 1
1!
#3080002
b1000 (
b0 /
b0 *
b0 #
b0 )
b0 +
b0 "
#3085002
0!
#3090002
b0 (
b0 &
b0 1
1!
0$
#3095002
0!
#3100002
1!
#3105002
0!
#3110002
1!
#3115002
0!
#3120002
1!
#3125002
b101 (
b101 /
0!
b1 %
b10 *
b10 #
b101 )
b11 +
b11 "
1$
#3130002
b1010 (
b101 &
b101 1
1!
#3135002
0!
#3140002
b1111 (
b1010 &
b1010 1
1!
#3145002
0!
#3150002
b10100 (
b1111 &
b1111 1
1!
#3155002
0!
#3160002
b11001 (
b10100 &
b10100 1
1!
#3165002
0!
#3170002
b11110 (
b11001 &
b11001 1
1!
#3175002
0!
#3180002
b100011 (
b11110 &
b11110 1
1!
#3185002
0!
#3190002
b101000 (
b100011 &
b100011 1
1!
#3195002
0!
#3200002
b101101 (
b101000 &
b101000 1
1!
#3205002
0!
#3210002
b110010 (
b101101 &
b101101 1
1!
#3215002
0!
#3220002
b110111 (
b110010 &
b110010 1
1!
#3225002
0!
#3230002
b111100 (
b110111 &
b110111 1
1!
#3235002
0!
#3240002
b1000001 (
b111100 &
b111100 1
1!
#3245002
0!
#3250002
1'
10
b110 (
b1 &
b1 1
1!
#3255002
0!
#3260002
0'
00
b1011 (
b110 &
b110 1
1!
#3265002
0!
#3270002
b10000 (
b1011 &
b1011 1
1!
#3275002
0!
#3280002
b10101 (
b10000 &
b10000 1
1!
#3285002
0!
#3290002
b11010 (
b10101 &
b10101 1
1!
#3295002
0!
#3300002
b11111 (
b11010 &
b11010 1
1!
#3305002
0!
#3310002
b100100 (
b11111 &
b11111 1
1!
#3315002
0!
#3320002
b101001 (
b100100 &
b100100 1
1!
#3325002
0!
#3330002
b101110 (
b101001 &
b101001 1
1!
#3335002
0!
#3340002
b110011 (
b101110 &
b101110 1
1!
#3345002
0!
#3350002
b111000 (
b110011 &
b110011 1
1!
#3355002
0!
#3360002
b111101 (
b111000 &
b111000 1
1!
#3365002
0!
#3370002
b1000010 (
b111101 &
b111101 1
1!
#3375002
0!
#3380002
1'
10
b111 (
b10 &
b10 1
1!
#3385002
0!
#3390002
0'
00
b1100 (
b111 &
b111 1
1!
#3395002
0!
#3400002
b10001 (
b1100 &
b1100 1
1!
#3405002
0!
#3410002
b10110 (
b10001 &
b10001 1
1!
#3415002
0!
#3420002
b11011 (
b10110 &
b10110 1
1!
#3425002
0!
#3430002
b100000 (
b11011 &
b11011 1
1!
#3435002
0!
#3440002
b100101 (
b100000 &
b100000 1
1!
#3445002
0!
#3450002
b101010 (
b100101 &
b100101 1
1!
#3455002
0!
#3460002
b101111 (
b101010 &
b101010 1
1!
#3465002
0!
#3470002
b110100 (
b101111 &
b101111 1
1!
#3475002
0!
#3480002
b111001 (
b110100 &
b110100 1
1!
#3485002
0!
#3490002
b111110 (
b111001 &
b111001 1
1!
#3495002
0!
#3500002
b1000011 (
b111110 &
b111110 1
1!
#3505002
0!
#3510002
1'
10
b1000 (
b11 &
b11 1
1!
#3515002
0!
#3520002
0'
00
b1101 (
b1000 &
b1000 1
1!
#3525002
0!
#3530002
b10010 (
b1101 &
b1101 1
1!
#3535002
0!
#3540002
b10111 (
b10010 &
b10010 1
1!
#3545002
0!
#3550002
b11100 (
b10111 &
b10111 1
1!
#3555002
0!
#3560002
b100001 (
b11100 &
b11100 1
1!
#3565002
0!
#3570002
b100110 (
b100001 &
b100001 1
1!
#3575002
0!
#3580002
b101011 (
b100110 &
b100110 1
1!
#3585002
0!
#3590002
b110000 (
b101011 &
b101011 1
1!
#3595002
0!
#3600002
b110101 (
b110000 &
b110000 1
1!
#3605002
0!
#3610002
b111010 (
b110101 &
b110101 1
1!
#3615002
0!
#3620002
b111111 (
b111010 &
b111010 1
1!
#3625002
0!
#3630002
b1000100 (
b111111 &
b111111 1
1!
#3635002
0!
#3640002
1'
10
b1001 (
b100 &
b100 1
1!
#3645002
0!
#3650002
0'
00
b1110 (
b1001 &
b1001 1
1!
#3655002
0!
#3660002
b10011 (
b1110 &
b1110 1
1!
#3665002
0!
#3670002
b11000 (
b10011 &
b10011 1
1!
#3675002
0!
#3680002
b11101 (
b11000 &
b11000 1
1!
#3685002
0!
#3690002
b100010 (
b11101 &
b11101 1
1!
#3695002
0!
#3700002
b100111 (
b100010 &
b100010 1
1!
#3705002
0!
#3710002
b101100 (
b100111 &
b100111 1
1!
#3715002
0!
#3720002
b110001 (
b101100 &
b101100 1
1!
#3725002
0!
#3730002
b110110 (
b110001 &
b110001 1
1!
#3735002
0!
#3740002
b111011 (
b110110 &
b110110 1
1!
#3745002
0!
#3750002
b1000000 (
b111011 &
b111011 1
1!
#3755002
0!
#3760002
1'
10
b101 (
b0 &
b0 1
1!
#3765002
0!
#3770002
0'
00
b1010 (
b101 &
b101 1
1!
#3775002
0!
#3780002
b1111 (
b1010 &
b1010 1
1!
#3785002
0!
#3790002
b10100 (
b1111 &
b1111 1
1!
#3795002
0!
#3800002
b11001 (
b10100 &
b10100 1
1!
#3805002
0!
#3810002
b11110 (
b11001 &
b11001 1
1!
#3815002
0!
#3820002
b100011 (
b11110 &
b11110 1
1!
#3825002
0!
#3830002
b101000 (
b100011 &
b100011 1
1!
#3835002
0!
#3840002
b101101 (
b101000 &
b101000 1
1!
#3845002
0!
#3850002
b110010 (
b101101 &
b101101 1
1!
#3855002
0!
#3860002
b110111 (
b110010 &
b110010 1
1!
#3865002
0!
