GP01/arith_operator/rtl/arith_operator.sv
module arith_operator
#(
    // * ------------------------------------------------------------------
    // * Parameters
    // * ------------------------------------------------------------------
    parameter                               NB_DATA        = 16 ,
    parameter                               NB_SEL         =  2
)
(
    // * ------------------------------------------------------------------
    // * Output
    // * ------------------------------------------------------------------
    output logic signed [ NB_DATA - 1 : 0 ] o_data_c            ,

    // * ------------------------------------------------------------------
    // * Inputs
    // * ------------------------------------------------------------------
    input  logic signed [ NB_DATA - 1 : 0 ] i_data_a            ,
    input  logic signed [ NB_DATA - 1 : 0 ] i_data_b            ,
    input  logic        [ NB_SEL  - 1 : 0 ] i_sel
);
    // * ------------------------------------------------------------------
    // * Vars
    // * ------------------------------------------------------------------
    logic        signed [ NB_DATA - 1 : 0 ] result              ;

    // * ------------------------------------------------------------------
    // * Muxing
    // * ------------------------------------------------------------------
    typedef enum logic [NB_SEL-1:0] {
        OP_ADDITION     = 2'b00 ,
        OP_SUBSTRACTION = 2'b01 ,
        OP_AND          = 2'b10 ,
        OP_OR           = 2'b11
    } op_options_e;

    always_comb
    begin : proc_op_selection
        case (i_sel)
            OP_ADDITION     : result = i_data_a + i_data_b ;
            OP_SUBSTRACTION : result = i_data_a - i_data_b ;
            OP_AND          : result = i_data_a & i_data_b ;
            OP_OR           : result = i_data_a | i_data_b ;
        endcase
    end

    // * ------------------------------------------------------------------
    // * Output assignment
    // * ------------------------------------------------------------------
    assign o_data_c = result;

    // * -------------------------------------------------
    // * Simulation define
    // * -------------------------------------------------
    `ifdef COCOTB_SIM
        initial begin
            $dumpfile ("dump.vcd");
            $dumpvars ();
            #1;
        end
    `endif
 endmodule

GP01/arith_operator/tb/dump.vcd
$date
	Mon Sep 16 23:25:54 2024
$end
$version
	Icarus Verilog
$end
$timescale
	1ps
$end
$scope module arith_operator $end
$var wire 16 ! i_data_a [15:0] $end
$var wire 16 " i_data_b [15:0] $end
$var wire 2 # i_sel [1:0] $end
$var wire 16 $ o_data_c [15:0] $end
$var parameter 32 % NB_DATA $end
$var parameter 32 & NB_SEL $end
$var reg 16 ' result [15:0] $end
$scope begin proc_op_selection $end
$upscope $end
$upscope $end
$enddefinitions $end
$comment Show the parameter values. $end
$dumpall
b10 &
b10000 %
$end
#0
$dumpvars
b0 '
b0 $
b0 #
b0 "
b0 !
$end
#26000
b1011000000111111 $
b1011000000111111 '
b111111101100110 "
b11000011011001 !
#39000
b11111111011101 $
b11111111011101 '
b1110111001100110 "
b101000101110111 !
#49000
b1110001001011010 $
b1110001001011010 '
b1101000110111011 "
b1000010011111 !
#86000
b1100010111000001 $
b1100010111000001 '
b1110011011000101 "
b1101111011111100 !
#112000
b1100001101000000 $
b1100001101000000 '
b1100011011110111 "
b1111110001001001 !
#139000
b1010101110111011 $
b1010101110111011 '
b1101000011110000 "
b1101101011001011 !
#178000
b101110101000100 $
b101110101000100 '
b1000011010110011 "
b1101011010010001 !
#211000
b1110001000110100 $
b1110001000110100 '
b110010111 "
b1110000010011101 !
#259000
b1110100100101000 $
b1110100100101000 '
b1011001000100010 "
b11011100000110 !
#304000
b11111100001111 $
b11111100001111 '
b1011111011011010 "
b1000000000110101 !
#334000
b101000111100011 $
b101000111100011 '
b1101001101101010 "
b111111001111001 !
#384000
b1111010011110001 $
b1111010011110001 '
b110010110100010 "
b1000111101001111 !
#402000
b10011110010111 $
b10011110010111 '
b1111000100101100 "
b11011001101011 !
#417000
b1110001011001111 $
b1110001011001111 '
b1101001011011001 "
b111111110110 !
#450000
b101000010000011 $
b101000010000011 '
b1011110000001 "
b11100100000010 !
#472000
b110001000110100 $
b110001000110100 '
b110010010000110 "
b1111110110101110 !
#514000
b1101110110000111 $
b1101110110000111 '
b110000010101001 "
b111110011011110 !
#537000
b1010001101101011 $
b1010001101101011 '
b1010110011 "
b1010000010111000 !
#551000
b1010111111000011 $
b1010111111000011 '
b1001101110101001 "
b1010000011010 !
#595000
b11111001110110 $
b11111001110110 '
b100011010000100 "
b1111011111110010 !
#624000
b1010010111001 $
b1010010111001 '
b100101111100101 "
b1100100011010100 !
#643000
b1000001000100010 $
b1000001000100010 '
b1111111111110101 "
b1000001000101101 !
#677000
b1011100100011111 $
b1011100100011111 '
b1010100111000101 "
b111101011010 !
#689000
b111000110000100 $
b111000110000100 '
b1100111011101111 "
b1010001010010101 !
#710000
b11110000100 $
b11110000100 '
b1000000000000000 "
b1000011110000100 !
#758000
b10011100010101 $
b10011100010101 '
b11110001011101 "
b1110101010111000 !
#807000
b1110110100111101 $
b1110110100111101 '
b1101111101001011 "
b110111110010 !
#842000
b1111011101101110 $
b1111011101101110 '
b111001101011 "
b1110100100000011 !
#877000
b110001011100110 $
b110001011100110 '
b1110111101001111 "
b111001110010111 !
#894000
b111101000001010 $
b111101000001010 '
b11000101001000 "
b100100011000010 !
#943000
b1011011001111 $
b1011011001111 '
b101011001101100 "
b1100000001100011 !
#987000
b1111111000001010 $
b1111111000001010 '
b1001010101100101 "
b110100010100101 !
#1035000
b1011110001010110 $
b1011110001010110 '
b1001100010110100 "
b10001110100010 !
#1046000
b10000010110100 $
b10000010110100 '
b110110000110010 "
b1011010010000010 !
#1081000
b100100011110101 $
b100100011110101 '
b1010100111011011 "
b1001111100011010 !
#1113000
b111110001001011 $
b111110001001011 '
b1101101111000000 "
b1010000010001011 !
#1149000
b10000011101001 $
b10000011101001 '
b111011111010111 "
b1010100100010010 !
#1196000
b111001101000 $
b111001101000 '
b101001001100 "
b10000011100 !
#1244000
b1101001110010010 $
b1101001110010010 '
b101010010111011 "
b111111011010111 !
#1289000
b100000011101011 $
b100000011101011 '
b1110100100001010 "
b101011111100001 !
#1307000
b1011100101111000 $
b1011100101111000 '
b1101011111111100 "
b1110000101111100 !
#1321000
b100110111000110 $
b100110111000110 '
b10111001110010 "
b1111101010100 !
#1371000
b100100110000111 $
b100100110000111 '
b101010001011010 "
b1111010100101101 !
#1401000
b1010101100000000 $
b1010101100000000 '
b1011111000000100 "
b1110110011111100 !
#1432000
b101101001000011 $
b101101001000011 '
b100001000010 "
b101001000000001 !
#1462000
b1010010111100100 $
b1010010111100100 '
b100100111001000 "
b101110000011100 !
#1487000
b1010000110000101 $
b1010000110000101 '
b1110000011101001 "
b1100000010011100 !
#1510000
b11011110111011 $
b11011110111011 '
b1000001010111001 "
b1011010100000010 !
#1523000
b101101000111000 $
b101101000111000 '
b1101111001111101 "
b111101110111011 !
#1573000
b1010100011100100 $
b1010100011100100 '
b1100101110011111 "
b1101110101000101 !
#1621000
b100111011100010 $
b100111011100010 '
b1010100110001000 "
b1010010101011010 !
#1647000
b10111110010001 $
b10111110010001 '
b111001100010001 "
b1011110010000000 !
#1688000
b1010110100001 $
b1010110100001 '
b1101000100111000 "
b100010001101001 !
#1713000
b1100100011111110 $
b1100100011111110 '
b1001110111001110 "
b10101100110000 !
#1748000
b100100100011001 $
b100100100011001 '
b1011000011011 "
b11001011111110 !
#1779000
b100101011110101 $
b100101011110101 '
b1010110001111000 "
b1001111001111101 !
#1828000
b1011110110011001 $
b1011110110011001 '
b110101001001001 "
b101001101010000 !
#1870000
b1110100011101101 $
b1110100011101101 '
b10011001101110 "
b1100001001111111 !
#1881000
b1110011010011011 $
b1110011010011011 '
b1000110100110 "
b1101010011110101 !
#1892000
b1010001100111101 $
b1010001100111101 '
b1011110011100101 "
b1110011001011000 !
#1930000
b1110101111110001 $
b1110101111110001 '
b1111100010110011 "
b1111001100111110 !
#1972000
b1101101000001100 $
b1101101000001100 '
b1000110110101001 "
b100110001100011 !
#1999000
b111001100010110 $
b111001100010110 '
b1111110100110 "
b101001101110000 !
#2049000
b110000011111000 $
b110000011111000 '
b11011001101000 "
b10101010010000 !
#2071000
b1010010110011000 $
b1010010110011000 '
b10001001100011 "
b1000001100110101 !
#2113000
b111100001100 $
b111100001100 '
b1011100100000110 "
b101011000000110 !
#2143000
b1011101001111001 $
b1011101001111001 '
b101110011001110 "
b101110110101011 !
#2166000
b110101001101110 $
b110101001101110 '
b1011000101110010 "
b1011100011111100 !
#2181000
b110101100101010 $
b110101100101010 '
b1011111000011110 "
b1010110100001100 !
#2227000
b1100110100001000 $
b1100110100001000 '
b1100110011010111 "
b110001 !
#2275000
b1010010100010111 $
b1010010100010111 '
b1111001010001 "
b1000011011000110 !
#2324000
b11101010101000 $
b11101010101000 '
b100011000010100 "
b1111010010010100 !
#2358000
b100101101011110 $
b100101101011110 '
b111011000100110 "
b1101010100111000 !
#2400000
b1110000011101011 $
b1110000011101011 '
b1100000101011001 "
b1111110010010 !
#2422000
b1001100110100101 $
b1001100110100101 '
b1111001100110 "
b111101100111111 !
#2464000
b1111010011010011 $
b1111010011010011 '
b1101010100101 "
b1101101000101110 !
#2514000
b100001100010000 $
b100001100010000 '
b10111011011100 "
b1010000110100 !
#2559000
b100111101100010 $
b100111101100010 '
b1000101101111010 "
b1100001111101000 !
#2586000
b1010111011000101 $
b1010111011000101 '
b1010001100011000 "
b101110101101 !
#2620000
b110100001100010 $
b110100001100010 '
b101100001 "
b110011100000001 !
#2635000
b1010010001011101 $
b1010010001011101 '
b1100111100001111 "
b1101010101001110 !
#2668000
b111001010101 $
b111001010101 '
b1101110011100 "
b1111001010111001 !
#2713000
b1100000011110010 $
b1100000011110010 '
b1111010111110001 "
b1100101100000001 !
#2751000
b1000000001101110 $
b1000000001101110 '
b1111111100110100 "
b1000000100111010 !
#2781000
b110110011000011 $
b110110011000011 '
b101111010101000 "
b111000011011 !
#2817000
b1000000011001111 $
b1000000011001111 '
b101000111001111 "
b10111100000000 !
#2850000
b110111010111010 $
b110111010111010 '
b110101101010001 "
b1101101001 !
#2892000
b1100110010100 $
b1100110010100 '
b1111101010001111 "
b1111100000101 !
#2931000
b1100000010110011 $
b1100000010110011 '
b1010111011110100 "
b1000110111111 !
#2954000
b11101011110010 $
b11101011110010 '
b11010010100010 "
b11001010000 !
#2969000
b10001100011100 $
b10001100011100 '
b10001110110 "
b1111010100110 !
#3019000
b1100100110000010 $
b1100100110000010 '
b1001001001100110 "
b11011100011100 !
#3063000
b1011111100100010 $
b1011111100100010 '
b1101001111010100 "
b1110101101001110 !
#3087000
b110110110010111 $
b110110110010111 '
b1100101101110100 "
b1010001000100011 !
#3125000
b1010111101101110 $
b1010111101101110 '
b1110100111000010 "
b1100010110101100 !
#3143000
b1101000101011111 $
b1101000101011111 '
b1011110100000 "
b1011100110111111 !
#3173000
b101101101011001 $
b101101101011001 '
b101111101 "
b101100111011100 !
#3220000
b111011010110110 $
b111011010110110 '
b11000010100000 "
b100011000010110 !
#3232000
b1101001100011100 $
b1101001100011100 '
b11100101110000 "
b1001100110101100 !
#3282000
b1001000000100111 $
b1001000000100111 '
b1000000111111101 "
b111000101010 !
#3323001
b0 $
b0 '
b0 "
b0 !
#3350001
b1101100100100011 $
b1101100100100011 '
b101010011100 "
b1110001110111111 !
b1 #
#3376001
b1110111111000101 $
b1110111111000101 '
b1000111101100000 "
b111111100100101 !
#3391001
b1101110111001111 $
b1101110111001111 '
b1100101010011001 "
b1010100001101000 !
#3413001
b11001011110101 $
b11001011110101 '
b101010111111011 "
b1000100011110000 !
#3434001
b1000000001111100 $
b1000000001111100 '
b110011001110100 "
b1110011011110000 !
#3462001
b1000010111100 $
b1000010111100 '
b1111011001111111 "
b11100111011 !
#3482001
b1110111110011101 $
b1110111110011101 '
b10101110101000 "
b1101101000101 !
#3496001
b1101101100101100 $
b1101101100101100 '
b1110001111111110 "
b1011111100101010 !
#3544001
b1100110011000001 $
b1100110011000001 '
b11111010100011 "
b101101100100 !
#3580001
b10111100000000 $
b10111100000000 '
b1110110010001001 "
b1101110001001 !
#3614001
b1101010011100 $
b1101010011100 '
b110000101000110 "
b111101111100010 !
#3627001
b101111111101 $
b101111111101 '
b10100111110101 "
b11010111110010 !
#3655001
b11000001110001 $
b11000001110001 '
b11111011111001 "
b110111101101010 !
#3704001
b1001111111010110 $
b1001111111010110 '
b10010101000 "
b1010010001111110 !
#3720001
b11110110001010 $
b11110110001010 '
b1110110100111101 "
b10101011000111 !
#3764001
b1011111000100011 $
b1011111000100011 '
b111100111100 "
b1100110101011111 !
#3809001
b1100110100011011 $
b1100110100011011 '
b1000111101011010 "
b101110001110101 !
#3841001
b1011100101001100 $
b1011100101001100 '
b111011111001011 "
b11000100010111 !
#3888001
b1000111100101111 $
b1000111100101111 '
b10000010000100 "
b1010111110110011 !
#3903001
b1000001111100000 $
b1000001111100000 '
b11011000011 "
b1000101010100011 !
#3918001
b1101100101011100 $
b1101100101011100 '
b110101011001000 "
b100010000100100 !
#3963001
b101111111001010 $
b101111111001010 '
b111110111111100 "
b1101110111000110 !
#3978001
b110111001111101 $
b110111001111101 '
b1010110101101000 "
b1101111100101 !
#4005001
b11001100011111 $
b11001100011111 '
b1111101000101010 "
b10110101001001 !
#4028001
b10010101110010 $
b10010101110010 '
b1010001011010 "
b11100111001100 !
#4071001
b1111111010111100 $
b1111111010111100 '
b1000100111101101 "
b1000100010101001 !
#4109001
b1100010000110111 $
b1100010000110111 '
b100000001001010 "
b10010000001 !
#4157001
b1000111011111 $
b1000111011111 '
b100010000000 "
b1101001011111 !
#4193001
b1011000010001011 $
b1011000010001011 '
b10101101001001 "
b1101101111010100 !
#4235001
b1010011100000111 $
b1010011100000111 '
b1111101111111 "
b1100011010000110 !
#4246001
b101111101111000 $
b101111101111000 '
b11100101101011 "
b1001100011100011 !
#4276001
b1001010010010001 $
b1001010010010001 '
b1100010001100101 "
b101100011110110 !
#4293001
b1010111000101 $
b1010111000101 '
b10011011010111 "
b11110010011100 !
#4334001
b1111110101101 $
b1111110101101 '
b1100101101111 "
b11100100011100 !
#4358001
b1111111101111101 $
b1111111101111101 '
b1010111100100011 "
b1010111010100000 !
#4375001
b1011110101011000 $
b1011110101011000 '
b100000010111100 "
b1111111000010100 !
#4407001
b1010000010110010 $
b1010000010110010 '
b111011110101010 "
b1100001011100 !
#4426001
b100111101111101 $
b100111101111101 '
b10010010011000 "
b111010000010101 !
#4438001
b101101011001100 $
b101101011001100 '
b1101101100000000 "
b11010111001100 !
#4476001
b101011001100 $
b101011001100 '
b110001001101111 "
b110110100111011 !
#4522001
b110011101101110 $
b110011101101110 '
b1101100001010 "
b1000001001111000 !
#4562001
b1000101011011011 $
b1000101011011011 '
b1111010101000101 "
b1000000000100000 !
#4596001
b100010001100101 $
b100010001100101 '
b11110110110011 "
b1000001000011000 !
#4636001
b1010100010101001 $
b1010100010101001 '
b1100110101110011 "
b111011000011100 !
#4660001
b101110010100110 $
b101110010100110 '
b1111011101111100 "
b101010000100010 !
#4692001
b1101011010001010 $
b1101011010001010 '
b1101011100101101 "
b1010110110110111 !
#4741001
b1010000011001001 $
b1010000011001001 '
b100100010001000 "
b1110100101010001 !
#4768001
b1011000010010010 $
b1011000010010010 '
b1101001010100011 "
b1000001100110101 !
#4796001
b1110011010011001 $
b1110011010011001 '
b111111101101001 "
b110011000000010 !
#4806001
b11110110001101 $
b11110110001101 '
b111110101000111 "
b1011101011010100 !
#4830001
b101111010001100 $
b101111010001100 '
b110000001010011 "
b1011111011011111 !
#4846001
b1010001100000001 $
b1010001100000001 '
b1101011001101101 "
b111100101101110 !
#4895001
b1110111000101001 $
b1110111000101001 '
b1000100001110101 "
b111011010011110 !
#4931001
b111100100001110 $
b111100100001110 '
b1110010011101111 "
b101110111111101 !
#4955001
b11101111110101 $
b11101111110101 '
b1111011101110110 "
b11001101101011 !
#4983001
b1100010101110100 $
b1100010101110100 '
b111001101111000 "
b11100011101100 !
#5006001
b101110110110100 $
b101110110110100 '
b1000010000000111 "
b1110000110111011 !
#5055001
b100001110011110 $
b100001110011110 '
b1001100100110110 "
b1101110011010100 !
#5092001
b100011111111100 $
b100011111111100 '
b1100111000001010 "
b1011000000110 !
#5140001
b1010101011101010 $
b1010101011101010 '
b1001101011101101 "
b100010111010111 !
#5163001
b1001101100101000 $
b1001101100101000 '
b11010100010000 "
b1101000000111000 !
#5197001
b10000101001101 $
b10000101001101 '
b1011000111100100 "
b1101001100110001 !
#5247001
b1101111010111011 $
b1101111010111011 '
b1101110110 "
b1110001000110001 !
#5274001
b1100010001110100 $
b1100010001110100 '
b101011101110111 "
b1101111101011 !
#5301001
b1111100101011 $
b1111100101011 '
b1100100100001001 "
b1110100000110100 !
#5322001
b110010100000100 $
b110010100000100 '
b101111000101001 "
b1100001100101101 !
#5355001
b1100100101110110 $
b1100100101110110 '
b110010000110010 "
b10110110101000 !
#5389001
b111001010011101 $
b111001010011101 '
b101001101 "
b111001111101010 !
#5417001
b1100010001001110 $
b1100010001001110 '
b1001001000000110 "
b101011001010100 !
#5449001
b1000011010100100 $
b1000011010100100 '
b1111111010110111 "
b1000010101011011 !
#5482001
b1001110100011001 $
b1001110100011001 '
b1011001101100111 "
b101000010000000 !
#5516001
b1100111110110000 $
b1100111110110000 '
b1101011111101001 "
b1010011110011001 !
#5529001
b101001110110001 $
b101001110110001 '
b1101010110011 "
b110111001100100 !
#5576001
b1111111010100101 $
b1111111010100101 '
b100110010100110 "
b100101101001011 !
#5588001
b100011000001100 $
b100011000001100 '
b1111010101001111 "
b11101101011011 !
#5620001
b101100011011111 $
b101100011011111 '
b11101110110010 "
b1001010010010001 !
#5646001
b1001001101101011 $
b1001001101101011 '
b1101110011100000 "
b111000001001011 !
#5674001
b101000011100101 $
b101000011100101 '
b11111101101101 "
b1001000001010010 !
#5705001
b1011001010010100 $
b1011001010010100 '
b101100011101000 "
b101101111100 !
#5737001
b110011110001011 $
b110011110001011 '
b100011001000000 "
b1010110111001011 !
#5778001
b1000101001110111 $
b1000101001110111 '
b1000011011000011 "
b1000100111010 !
#5826001
b1001110000101010 $
b1001110000101010 '
b1111101011101011 "
b1001011100010101 !
#5854001
b1011001001011110 $
b1011001001011110 '
b1110100010110110 "
b1001101100010100 !
#5892001
b1011001111010001 $
b1011001111010001 '
b1010111100001000 "
b110001011011001 !
#5928001
b1110101011000001 $
b1110101011000001 '
b1001000001011100 "
b111101100011101 !
#5974001
b1011111000010001 $
b1011111000010001 '
b1010100110111000 "
b110011111001001 !
#5988001
b1111000111110001 $
b1111000111110001 '
b1100111000111011 "
b1100000000101100 !
#6028001
b1111001000010001 $
b1111001000010001 '
b1111000000110001 "
b1110001001000010 !
#6066001
b111101001011001 $
b111101001011001 '
b10010101000100 "
b1001111110011101 !
#6115001
b1100011000010101 $
b1100011000010101 '
b1000000010000101 "
b100011010011010 !
#6151001
b100101101110001 $
b100101101110001 '
b100000101010110 "
b1000110011000111 !
#6185001
b101100001010011 $
b101100001010011 '
b100110101111100 "
b1010010111001111 !
#6228001
b10011000100010 $
b10011000100010 '
b1011010011000000 "
b1101101011100010 !
#6254001
b1011101111010000 $
b1011101111010000 '
b1100010001000110 "
b1000000000010110 !
#6304001
b101010010010111 $
b101010010010111 '
b1111000110110101 "
b100011001001100 !
#6348001
b110100100111 $
b110100100111 '
b10000110111111 "
b10111011100110 !
#6398001
b110000010000 $
b110000010000 '
b110000000101110 "
b110110000111110 !
#6440001
b1100111100010010 $
b1100111100010010 '
b101011111000000 "
b10011011010010 !
#6450001
b100110010000110 $
b100110010000110 '
b111001110110111 "
b1100000000111101 !
#6464001
b111011110001000 $
b111011110001000 '
b1001010000100110 "
b101110101110 !
#6488002
b0 $
b0 '
b0 "
b0 !
b0 #
#6503002
b1001110000000001 $
b1001110000000001 '
b1001110011011101 "
b1011111100000001 !
b10 #
#6516002
b1000001000011 $
b1000001000011 '
b1000101011011 "
b111001011000011 !
#6532002
b1100100011001001 $
b1100100011001001 '
b1101100111001011 "
b1110110011001001 !
#6581002
b1000100000001000 $
b1000100000001000 '
b1101100100011000 "
b1000111010101010 !
#6627002
b110001110101101 $
b110001110101101 '
b1110101110101111 "
b110011110111101 !
#6670002
b1000010001100000 $
b1000010001100000 '
b1010110101100010 "
b1100011001101101 !
#6719002
b1010100011010000 $
b1010100011010000 '
b1011110011110000 "
b1110100011011100 !
#6762002
b1000000100000 $
b1000000100000 '
b11110100100010 "
b101001011101000 !
#6783002
b110000100010001 $
b110000100010001 '
b111000100010001 "
b1110010101111001 !
#6813002
b101100010110000 $
b101100010110000 '
b101100011110100 "
b101101010110001 !
#6837002
b110000010100110 $
b110000010100110 '
b110000010100110 "
b110101010101110 !
#6879002
b1000000000100010 $
b1000000000100010 '
b1000100000100110 "
b1011001000100011 !
#6905002
b10100000000 $
b10100000000 '
b101011100111010 "
b10110000000 !
#6918002
b1111011000100100 $
b1111011000100100 '
b1111111100101100 "
b1111011000100111 !
#6929002
b1000110010101 $
b1000110010101 '
b101000110110101 "
b1101110010101 !
#6977002
b100000000000001 $
b100000000000001 '
b1100000010011111 "
b110000101100001 !
#7010002
b1101101000100 $
b1101101000100 '
b11111111100110 "
b1101101001101 !
#7058002
b1000010011101101 $
b1000010011101101 '
b1100010011111101 "
b1010010011101101 !
#7093002
b100001000 $
b100001000 '
b1001100001001 "
b1110000101011110 !
#7130002
b1100000000 $
b1100000000 '
b1100111100001000 "
b1001100110011 !
#7173002
b110000010000010 $
b110000010000010 '
b110000011110110 "
b1110011110001010 !
#7222002
b1101000000000011 $
b1101000000000011 '
b1101001100000111 "
b1111110011001011 !
#7262002
b10011010000 $
b10011010000 '
b1010010111010000 "
b11011011001 !
#7287002
b1000000010 $
b1000000010 '
b1011001000111111 "
b100001000000010 !
#7320002
b1000000100 $
b1000000100 '
b1000000100 "
b1011111100111101 !
#7360002
b100000011000010 $
b100000011000010 '
b1100001111110111 "
b101000011001010 !
#7395002
b10000000000 $
b10000000000 '
b110110111111100 "
b11000000001 !
#7432002
b110010010110110 $
b110010010110110 '
b110010011111110 "
b1110011110110111 !
#7449002
b100010000000 $
b100010000000 '
b1100101010010100 "
b11110111001000 !
#7479002
b1000100000000000 $
b1000100000000000 '
b1010110101000000 "
b1101100010010100 !
#7505002
b0 $
b0 '
b10100101000010 "
b101000 !
#7555002
b1110001000010101 $
b1110001000010101 '
b1110011100110101 "
b1111101010010101 !
#7600002
b1100000000000110 $
b1100000000000110 '
b1100000000000110 "
b1100110010000111 !
#7625002
b100000000010001 $
b100000000010001 '
b110100010110001 "
b101011101010011 !
#7640002
b100111101001001 $
b100111101001001 '
b1101111101011011 "
b110111101101101 !
#7668002
b101111010010000 $
b101111010010000 '
b101111011111010 "
b101111110010000 !
#7683002
b11010110000 $
b11010110000 '
b11011011110101 "
b1000011010110000 !
#7700002
b100000001 $
b100000001 '
b1111101000101 "
b10000100001001 !
#7710002
b100100011 $
b100100011 '
b101100111100011 "
b100101011 !
#7755002
b1100101100110100 $
b1100101100110100 '
b1111101100111100 "
b1100111110110100 !
#7790002
b111110010000 $
b111110010000 '
b111110111111 "
b11111111010000 !
#7815002
b11010000000 $
b11010000000 '
b1101011010100000 "
b111011010110 !
#7857002
b10000 $
b10000 '
b10110111011001 "
b1101001000110110 !
#7898002
b1000001000000000 $
b1000001000000000 '
b1000011001010100 "
b1011101000000001 !
#7937002
b1100001011000000 $
b1100001011000000 '
b1111111011101011 "
b1100001011000100 !
#7960002
b10100010 $
b10100010 '
b1000010010101010 "
b111100010110010 !
#7986002
b100001000000 $
b100001000000 '
b110100001101000 "
b1111011010101 !
#7998002
b1001011100000111 $
b1001011100000111 '
b1101011101000111 "
b1001111110110111 !
#8036002
b100000000111000 $
b100000000111000 '
b1101100010111010 "
b110011101111001 !
#8082002
b1001000010111010 $
b1001000010111010 '
b1001110110111010 "
b1011001011111011 !
#8107002
b10000100000 $
b10000100000 '
b100010010100000 "
b10111100100011 !
#8140002
b1000000000000000 $
b1000000000000000 '
b1110000110101000 "
b1000101001010001 !
#8153002
b100000000011001 $
b100000000011001 '
b101110100011111 "
b100000010011001 !
#8183002
b1000000000000100 $
b1000000000000100 '
b1110001011000100 "
b1000010100010100 !
#8193002
b110100000000000 $
b110100000000000 '
b110100101001010 "
b110111010000100 !
#8241002
b110010001000 $
b110010001000 '
b1100110010011101 "
b111110001000 !
#8285002
b1011000000000 $
b1011000000000 '
b1101011000010100 "
b1011010001000 !
#8303002
b100000000001000 $
b100000000001000 '
b100010111001011 "
b1111100000011000 !
#8331002
b10010000001 $
b10010000001 '
b100110011001101 "
b1011011110010001 !
#8381002
b10100000001000 $
b10100000001000 '
b1110110100001100 "
b11101011011000 !
#8407002
b10011001000000 $
b10011001000000 '
b1110011001110000 "
b10111001001001 !
#8448002
b101000 $
b101000 '
b111001 "
b1101000110101100 !
#8470002
b100100000000 $
b100100000000 '
b110100101100010 "
b1000110100001100 !
#8482002
b110010000 $
b110010000 '
b1000111010000 "
b100110110111000 !
#8498002
b10000110100 $
b10000110100 '
b10110011110110 "
b10100110100 !
#8542002
b1000111000000 $
b1000111000000 '
b111001111110010 "
b1110111000000 !
#8590002
b1000000000001000 $
b1000000000001000 '
b1001001001101010 "
b1100110100001101 !
#8618002
b100000110000001 $
b100000110000001 '
b101010110000101 "
b1110000110111001 !
#8655002
b11000001000 $
b11000001000 '
b1010011000001111 "
b100111011011000 !
#8667002
b1000000001001 $
b1000000001001 '
b1001011101001 "
b1001110000001101 !
#8699002
b1110100110110100 $
b1110100110110100 '
b1110101110110111 "
b1111100110111100 !
#8714002
b10000111000010 $
b10000111000010 '
b1111100111011110 "
b10011111100011 !
#8743002
b100000000 $
b100000000 '
b100111110000100 "
b11000101010000 !
#8762002
b1010101010000010 $
b1010101010000010 '
b1011101010000110 "
b1110101111110010 !
#8812002
b1010 $
b1010 '
b10001001011 "
b1110000110011110 !
#8826002
b1001010001000100 $
b1001010001000100 '
b1001110111010100 "
b1001010001000101 !
#8862002
b1000000000000000 $
b1000000000000000 '
b1010000010000011 "
b1001011001101100 !
#8873002
b1001000 $
b1001000 '
b110110001011100 "
b1000001011001010 !
#8922002
b10001101 $
b10001101 '
b111010110101111 "
b1000101010001101 !
#8952002
b1000000001000000 $
b1000000001000000 '
b1000100101100000 "
b1001010001010001 !
#8968002
b11001101000000 $
b11001101000000 '
b11001111010000 "
b1111101101100111 !
#8987002
b10000001000000 $
b10000001000000 '
b1010000001111101 "
b111010001000010 !
#9034002
b10000000011000 $
b10000000011000 '
b10000010111100 "
b111011100011011 !
#9068002
b100000000 $
b100000000 '
b100100011 "
b1110000110011000 !
#9082002
b110000010000010 $
b110000010000010 '
b110111010000110 "
b111000111010010 !
#9110002
b100011001000000 $
b100011001000000 '
b1110111001110100 "
b101011101000000 !
#9122002
b10001000001 $
b10001000001 '
b10101110011 "
b1001010011001101 !
#9136002
b110100011011010 $
b110100011011010 '
b110111011011111 "
b111100011111010 !
#9154002
b101000 $
b101000 '
b100101001 "
b1101001001101010 !
#9191002
b1010010100001001 $
b1010010100001001 '
b1010010110111001 "
b1010010101001001 !
#9229002
b101000000100 $
b101000000100 '
b1010101001100101 "
b1111110001100 !
#9263002
b1100000001010 $
b1100000001010 '
b1101101000011110 "
b11110100101011 !
#9301002
b10000100000 $
b10000100000 '
b10010101100100 "
b1110000110001 !
#9326002
b1011100001000000 $
b1011100001000000 '
b1011100101000000 "
b1111100011011101 !
#9342002
b11110101100100 $
b11110101100100 '
b11110101110101 "
b11111111100100 !
#9357002
b1000000100100010 $
b1000000100100010 '
b1100100111100011 "
b1010011100110010 !
#9402002
b1011000000110000 $
b1011000000110000 '
b1011000010111001 "
b1111101001110100 !
#9418002
b100000001000010 $
b100000001000010 '
b1100101101010110 "
b101000001001010 !
#9459002
b10101000001 $
b10101000001 '
b11101100011 "
b1101010101001101 !
#9504002
b1000000011000100 $
b1000000011000100 '
b1000000011101100 "
b1000111011010100 !
#9526003
b0 $
b0 '
b0 "
b0 !
b0 #
#9576003
b111101011111111 $
b111101011111111 '
b111101001111100 "
b10101010001011 !
b11 #
#9611003
b110101111111101 $
b110101111111101 '
b1001000000 "
b110101111111101 !
#9630003
b1111110011111011 $
b1111110011111011 '
b111110011111001 "
b1001100001101010 !
#9679003
b1111110110101111 $
b1111110110101111 '
b1011010110000111 "
b101100110101010 !
#9721003
b1111011111101110 $
b1111011111101110 '
b1111001111101000 "
b1111010111100110 !
#9733003
b1010101110010111 $
b1010101110010111 '
b10001110010011 "
b1010101110010101 !
#9780003
b100111111011111 $
b100111111011111 '
b100110011100 "
b100111111001111 !
#9813003
b1111000111111111 $
b1111000111111111 '
b1110000111011111 "
b1011000010101101 !
#9850003
b110111110110010 $
b110111110110010 '
b10001110010010 "
b110111110110000 !
#9883003
b1001111110111111 $
b1001111110111111 '
b1011110110111 "
b1000100000011101 !
#9923003
b100001011101111 $
b100001011101111 '
b100001001100100 "
b11001111 !
#9950003
b1110111111110111 $
b1110111111110111 '
b1000111100110100 "
b1110100011000011 !
#9973003
b111110111111011 $
b111110111111011 '
b11110111110000 "
b101000010101011 !
#10022003
b1101111111011110 $
b1101111111011110 '
b1101111111011000 "
b1101011011000110 !
#10056003
b1111111111011111 $
b1111111111011111 '
b1100010111011011 "
b1111111100001111 !
#10074003
b1111111111111101 $
b1111111111111101 '
b1110101111111001 "
b11010001110100 !
#10105003
b1110110101111111 $
b1110110101111111 '
b1000010100001101 "
b1110100001110110 !
#10149003
b1111100110111111 $
b1111100110111111 '
b1011100100111101 "
b1100100010001110 !
#10189003
b111011101110111 $
b111011101110111 '
b11001100010101 "
b101010001100010 !
#10215003
b111011011110010 $
b111011011110010 '
b111001010100000 "
b111010001010010 !
#10261003
b1111101101011111 $
b1111101101011111 '
b1111001101001011 "
b101100001011110 !
#10282003
b1111111010010010 $
b1111111010010010 '
b111001000000010 "
b1111111010010010 !
#10308003
b11111101100011 $
b11111101100011 '
b10101001100001 "
b1110100000011 !
#10355003
b111100011110110 $
b111100011110110 '
b1000000110110 "
b111100011000010 !
#10392003
b1110011001110110 $
b1110011001110110 '
b1100010001110010 "
b1010001001110110 !
