GP01/iir_filter/rtl/iir_filter.sv
module iir_filter#(
    // * -------------------------------------------------------------------------------------------
    // * Parameters
    // * -------------------------------------------------------------------------------------------
    parameter                                                                NB_DATA_IN       =  8 ,
    parameter                                                                NB_DATA_OUT      = 11 ,
    parameter                                                                N_INPUT_SAMPLES  =  3 ,
    parameter                                                                N_OUTPUT_SAMPLES =  2 ,
    parameter                                                                ADD_OUTPUT_PIPE  =  0
)
(
    // * -------------------------------------------------------------------------------------------
    // * Outputs
    // * -------------------------------------------------------------------------------------------
    output logic signed [ NB_DATA_OUT                              - 1 : 0 ] o_data                ,

    // * -------------------------------------------------------------------------------------------
    // * Inputs
    // * -------------------------------------------------------------------------------------------
    input  logic signed [ NB_DATA_IN                               - 1 : 0 ] i_data                ,

    // * -------------------------------------------------------------------------------------------
    // * Clock and reset
    // * -------------------------------------------------------------------------------------------
    input  logic                                                             i_reset               ,
    input  logic                                                             i_clock
) ;
    // * -------------------------------------------------------------------------------------------
    // * Internal logics
    // * -------------------------------------------------------------------------------------------
    logic  signed       [ N_INPUT_SAMPLES  - 1 : 0 ] [ NB_DATA_IN  - 1 : 0 ] x_samples             ;
    logic  signed       [ N_INPUT_SAMPLES  - 1 : 0 ] [ NB_DATA_OUT - 1 : 0 ] partial_sums_x        ;
    logic  signed       [ N_OUTPUT_SAMPLES - 1 : 0 ] [ NB_DATA_OUT - 1 : 0 ] y_samples             ;
    logic  signed       [ N_OUTPUT_SAMPLES - 1 : 0 ] [ NB_DATA_OUT - 1 : 0 ] partial_sums_y        ;
    logic  signed       [ N_OUTPUT_SAMPLES - 1 : 0 ] [ NB_DATA_OUT - 1 : 0 ] y_samples_divided     ;
    logic  signed       [ NB_DATA_OUT                              - 1 : 0 ] ed_result             ;
    logic  signed       [ NB_DATA_OUT                              - 1 : 0 ] pipe_result           ;

    // * -------------------------------------------------------------------------------------------
    // * Output divisions
    // * -------------------------------------------------------------------------------------------
    generate
        for (genvar g_sample = 0 ; g_sample < N_OUTPUT_SAMPLES ; g_sample++)
        begin : gen_assigns_divisions
            assign y_samples_divided[g_sample] = y_samples[g_sample] >>> 1;
        end
    endgenerate

    // * -------------------------------------------------------------------------------------------
    // * Result calculation
    // * -------------------------------------------------------------------------------------------
    assign partial_sums_x[0] = i_data - x_samples[0];
    generate
        for (genvar g_sum_xi = 1 ; g_sum_xi < N_INPUT_SAMPLES ; g_sum_xi++)
        begin : gen_xi_partial_sums
            assign partial_sums_x[g_sum_xi] = partial_sums_x[g_sum_xi-1] + x_samples[g_sum_xi];
        end
    endgenerate

    assign partial_sums_y[0] = y_samples_divided[0];
    generate
        for (genvar g_sum_yi = 1 ; g_sum_yi < N_OUTPUT_SAMPLES ; g_sum_yi++)
        begin : gen_yi_partial_sums
            assign partial_sums_y[g_sum_yi] = partial_sums_y[g_sum_yi-1] + y_samples_divided[g_sum_yi];
        end
    endgenerate

    assign ed_result = partial_sums_x[N_INPUT_SAMPLES-1] + partial_sums_y[N_OUTPUT_SAMPLES-1];

    // * -------------------------------------------------------------------------------------------
    // * Sampling
    // * -------------------------------------------------------------------------------------------
    always_ff @(posedge i_clock)
    begin : proc_filtering
        if (i_reset) begin
            x_samples <= '0;
            y_samples <= '0;
        end else begin
            x_samples <= {x_samples        [N_INPUT_SAMPLES -2:0], i_data   };
            y_samples <= {y_samples_divided[N_OUTPUT_SAMPLES-2:0], ed_result};
        end
    end

    // * -------------------------------------------------------------------------------------------
    // * Optional pipe out
    // * -------------------------------------------------------------------------------------------
    if (ADD_OUTPUT_PIPE)
    begin : gen_pipe_out
        always_ff @(i_clock)
        begin : proc_pipe_out
            pipe_result <= ed_result;
        end
    end else
    begin : gen_direct_out
        assign pipe_result = ed_result;
    end

    // * -------------------------------------------------------------------------------------------
    // * Output assignment
    // * -------------------------------------------------------------------------------------------
    assign o_data = pipe_result;

    // * -------------------------------------------------------------------------------------------
    // * Simulation define
    // * -------------------------------------------------------------------------------------------
    `ifdef COCOTB_SIM
        initial begin
            $dumpfile ("dump.vcd");
            $dumpvars ();
            #1;
        end
    `endif
endmodule

GP01/iir_filter/tb/dump.vcd
$date
	Tue Sep 17 22:33:43 2024
$end
$version
	Icarus Verilog
$end
$timescale
	1ps
$end
$scope module iir_filter $end
$var wire 1 ! i_clock $end
$var wire 8 " i_data [7:0] $end
$var wire 1 # i_reset $end
$var wire 11 $ o_data [10:0] $end
$var wire 22 % y_samples_divided [21:0] $end
$var wire 11 & pipe_result [10:0] $end
$var wire 22 ' partial_sums_y [21:0] $end
$var wire 33 ( partial_sums_x [32:0] $end
$var wire 11 ) ed_result [10:0] $end
$var parameter 32 * ADD_OUTPUT_PIPE $end
$var parameter 32 + NB_DATA_IN $end
$var parameter 32 , NB_DATA_OUT $end
$var parameter 32 - N_INPUT_SAMPLES $end
$var parameter 32 . N_OUTPUT_SAMPLES $end
$var reg 24 / x_samples [23:0] $end
$var reg 22 0 y_samples [21:0] $end
$scope begin gen_assigns_divisions[0] $end
$var parameter 2 1 g_sample $end
$upscope $end
$scope begin gen_assigns_divisions[1] $end
$var parameter 2 2 g_sample $end
$upscope $end
$scope begin gen_direct_out $end
$upscope $end
$scope begin gen_xi_partial_sums[1] $end
$var parameter 2 3 g_sum_xi $end
$upscope $end
$scope begin gen_xi_partial_sums[2] $end
$var parameter 3 4 g_sum_xi $end
$upscope $end
$scope begin gen_yi_partial_sums[1] $end
$var parameter 2 5 g_sum_yi $end
$upscope $end
$scope begin proc_filtering $end
$upscope $end
$upscope $end
$enddefinitions $end
$comment Show the parameter values. $end
$dumpall
b1 5
b10 4
b1 3
b1 2
b0 1
b10 .
b11 -
b1011 ,
b1000 +
b0 *
$end
#0
$dumpvars
bx 0
bx00000000 /
bx )
bx00000000000 (
bx '
bx &
bx %
bx $
0#
b0 "
1!
$end
#5000
0!
#10000
1#
bx0000000000000000000000 (
bx0000000000000000 /
1!
#15000
0!
#20000
b0 $
b0 &
b0 )
b0 '
b0 %
b0 (
b0 0
b0 /
1!
#25000
0!
#30000
0#
1!
#35000
0!
#40000
b11110000000 $
b11110000000 &
b11110000000 )
b111100000001111000000011110000000 (
b10000000 "
1!
#45000
0!
#50000
b11111000000 $
b11111000000 &
b11111000000 )
b1111100000011111000000 '
b11111000000 %
b0 (
b11110000000 0
b10000000 /
1!
#55000
0!
#60000
b1111100000011111100000 '
b11101000000 $
b11101000000 &
b11101000000 )
b1111110000011111100000 %
b111100000001111000000000000000000 (
b1111100000011111000000 0
b1000000010000000 /
1!
#65000
0!
#70000
b1111001000011110100000 '
b1111111000011110100000 %
b11010010000 $
b11010010000 &
b11010010000 )
b111000000001111000000000000000000 (
b1111110000011101000000 0
b100000001000000010000000 /
1!
#75000
0!
#80000
b11000011000 $
b11000011000 &
b11000011000 )
b1110001100011101001000 '
b1111101000011101001000 %
b1111010000011010010000 0
1!
#85000
0!
#90000
b10110110000 $
b10110110000 &
b10110110000 )
b1101011000011100001100 '
b1111010010011100001100 %
b1110100100011000011000 0
1!
#95000
0!
#100000
b10101011110 $
b10101011110 &
b10101011110 )
b1100101111011011011000 '
b1111000011011011011000 %
b1110000110010110110000 0
1!
#105000
0!
#110000
b10100011011 $
b10100011011 &
b10100011011 )
b1100001101111010101111 '
b1110110110011010101111 %
b1101101100010101011110 0
1!
#115000
0!
#120000
b10011100100 $
b10011100100 &
b10011100100 )
b1011110010011010001101 '
b1110101011111010001101 %
b1101010111110100011011 0
1!
#125000
0!
#130000
b10010111000 $
b10010111000 &
b10010111000 )
b1011011100011001110010 '
b1110100011011001110010 %
b1101000110110011100100 0
1!
#135000
0!
#140000
b10010010101 $
b10010010101 &
b10010010101 )
b1011001010111001011100 '
b1110011100111001011100 %
b1100111001010010111000 0
1!
#145000
0!
#150000
b10001111000 $
b10001111000 &
b10001111000 )
b1010111100011001001010 '
b1110010111011001001010 %
b1100101110010010010101 0
1!
#155000
0!
#160000
b10001100001 $
b10001100001 &
b10001100001 )
b1010110000111000111100 '
b1110010010111000111100 %
b1100100101010001111000 0
1!
#165000
0!
#170000
b10001001110 $
b10001001110 &
b10001001110 )
b1010100111011000110000 '
b1110001111011000110000 %
b1100011110010001100001 0
1!
#175000
0!
#180000
b10000111111 $
b10000111111 &
b10000111111 )
b1010011111111000100111 '
b1110001100011000100111 %
b1100011000010001001110 0
1!
#185000
0!
#190000
b10000110010 $
b10000110010 &
b10000110010 )
b1010011001011000011111 '
b1110001001111000011111 %
b1100010011110000111111 0
1!
#195000
0!
#200000
b10000101000 $
b10000101000 &
b10000101000 )
b1010010100011000011001 '
b1110000111111000011001 %
b1100001111110000110010 0
1!
#205000
0!
#210000
b10000100000 $
b10000100000 &
b10000100000 )
b1010010000011000010100 '
b1110000110011000010100 %
b1100001100110000101000 0
1!
#215000
0!
#220000
b10000011010 $
b10000011010 &
b10000011010 )
b1010001101011000010000 '
b1110000101011000010000 %
b1100001010010000100000 0
1!
#225000
0!
#230000
b10000010101 $
b10000010101 &
b10000010101 )
b1010001010111000001101 '
b1110000100011000001101 %
b1100001000010000011010 0
1!
#235000
0!
#240000
b10000010000 $
b10000010000 &
b10000010000 )
b1010001000011000001010 '
b1110000011011000001010 %
b1100000110110000010101 0
1!
#245000
0!
#250000
b10000001101 $
b10000001101 &
b10000001101 )
b1010000110111000001000 '
b1110000010111000001000 %
b1100000101010000010000 0
1!
#255000
0!
#260000
b10000001010 $
b10000001010 &
b10000001010 )
b1010000101011000000110 '
b1110000010011000000110 %
b1100000100010000001101 0
1!
#265000
0!
#270000
b10000001000 $
b10000001000 &
b10000001000 )
b1010000100011000000101 '
b1110000001111000000101 %
b1100000011010000001010 0
1!
#275000
0!
#280000
b10000000110 $
b10000000110 &
b10000000110 )
b1010000011011000000100 '
b1110000001011000000100 %
b1100000010110000001000 0
1!
#285000
0!
#290000
b10000000101 $
b10000000101 &
b10000000101 )
b1010000010111000000011 '
b1110000001011000000011 %
b1100000010010000000110 0
1!
#295000
0!
#300000
b10000000011 $
b10000000011 &
b10000000011 )
b1010000001111000000010 '
b1110000000111000000010 %
b1100000001110000000101 0
1!
#305000
0!
#310000
b10000000010 $
b10000000010 &
b10000000010 )
b1010000001011000000001 '
b1110000000111000000001 %
b1100000001010000000011 0
1!
#315000
0!
#320000
b10000000001 $
b10000000001 &
b10000000001 )
b1010000000111000000001 '
b1110000000011000000001 %
b1100000000110000000010 0
1!
#325000
0!
#330000
b10000000000 $
b10000000000 &
b10000000000 )
b1010000000011000000000 '
b1110000000011000000000 %
b1100000000110000000001 0
1!
#335000
0!
#340000
b1100000000010000000000 0
1!
