GP01/iir_filter/rtl/iir_filter.sv
module iir_filter#(
    // * -------------------------------------------------------------------------------------------
    // * Parameters
    // * -------------------------------------------------------------------------------------------
    parameter                                                                NB_DATA_IN       =  8 ,
    parameter                                                                NB_DATA_OUT      = 12 ,
    parameter                                                                N_INPUT_SAMPLES  =  3 ,
    parameter                                                                N_OUTPUT_SAMPLES =  2 ,
    parameter                                                                ADD_OUTPUT_PIPE  =  0
)
(
    // * -------------------------------------------------------------------------------------------
    // * Outputs
    // * -------------------------------------------------------------------------------------------
    output logic signed [ NB_DATA_OUT                              - 1 : 0 ] o_data                ,

    // * -------------------------------------------------------------------------------------------
    // * Inputs
    // * -------------------------------------------------------------------------------------------
    input  logic signed [ NB_DATA_IN                               - 1 : 0 ] i_data                ,

    // * -------------------------------------------------------------------------------------------
    // * Clock and reset
    // * -------------------------------------------------------------------------------------------
    input  logic                                                             i_reset               ,
    input  logic                                                             i_clock
) ;
    // * -------------------------------------------------------------------------------------------
    // * Internal logics
    // * -------------------------------------------------------------------------------------------
    logic  signed       [ N_INPUT_SAMPLES  - 1 : 0 ] [ NB_DATA_IN  - 1 : 0 ] x_samples             ;
    logic  signed       [ N_INPUT_SAMPLES  - 1 : 0 ] [ NB_DATA_OUT - 1 : 0 ] partial_sums_x        ;
    logic  signed       [ N_OUTPUT_SAMPLES - 1 : 0 ] [ NB_DATA_OUT - 1 : 0 ] y_samples             ;
    logic  signed       [ N_OUTPUT_SAMPLES - 1 : 0 ] [ NB_DATA_OUT - 1 : 0 ] partial_sums_y        ;
    logic  signed       [ N_OUTPUT_SAMPLES - 1 : 0 ] [ NB_DATA_OUT - 1 : 0 ] y_samples_divided     ;
    logic  signed       [ NB_DATA_OUT                              - 1 : 0 ] ed_result             ;
    logic  signed       [ NB_DATA_OUT                              - 1 : 0 ] pipe_result           ;

    // * -------------------------------------------------------------------------------------------
    // * Output divisions
    // * -------------------------------------------------------------------------------------------
    generate
        for (genvar g_sample = 0 ; g_sample < N_OUTPUT_SAMPLES ; g_sample++)
        begin : gen_assigns_divisions
            assign y_samples_divided[g_sample] = y_samples[g_sample] >>> 1;
        end
    endgenerate

    // * -------------------------------------------------------------------------------------------
    // * Result calculation
    // * -------------------------------------------------------------------------------------------
    assign partial_sums_x[0] = i_data - x_samples[0];
    generate
        for (genvar g_sum_xi = 1 ; g_sum_xi < N_INPUT_SAMPLES ; g_sum_xi++)
        begin : gen_xi_partial_sums
            assign partial_sums_x[g_sum_xi] = partial_sums_x[g_sum_xi-1] + x_samples[g_sum_xi];
        end
    endgenerate

    assign partial_sums_y[0] = y_samples_divided[0];
    generate
        for (genvar g_sum_yi = 1 ; g_sum_yi < N_OUTPUT_SAMPLES ; g_sum_yi++)
        begin : gen_yi_partial_sums
            assign partial_sums_y[g_sum_yi] = partial_sums_y[g_sum_yi-1] + y_samples_divided[g_sum_yi];
        end
    endgenerate

    assign ed_result = partial_sums_x[N_INPUT_SAMPLES-1] + partial_sums_y[N_OUTPUT_SAMPLES-1];

    // * -------------------------------------------------------------------------------------------
    // * Sampling
    // * -------------------------------------------------------------------------------------------
    always_ff @(posedge i_clock)
    begin : proc_filtering
        if (i_reset) begin
            x_samples <= '0;
            y_samples <= '0;
        end else begin
            x_samples <= {x_samples        [N_INPUT_SAMPLES -2:0], i_data   };
            y_samples <= {y_samples_divided[N_OUTPUT_SAMPLES-2:0], ed_result};
        end
    end

    // * -------------------------------------------------------------------------------------------
    // * Optional pipe out
    // * -------------------------------------------------------------------------------------------
    if (ADD_OUTPUT_PIPE)
    begin : gen_pipe_out
        always_ff @(i_clock)
        begin : proc_pipe_out
            pipe_result <= ed_result;
        end
    end else
    begin : gen_direct_out
        assign pipe_result = ed_result;
    end

    // * -------------------------------------------------------------------------------------------
    // * Output assignment
    // * -------------------------------------------------------------------------------------------
    assign o_data = pipe_result;

    // * -------------------------------------------------------------------------------------------
    // * Simulation define
    // * -------------------------------------------------------------------------------------------
    `ifdef COCOTB_SIM
        initial begin
            $dumpfile ("dump.vcd");
            $dumpvars ();
            #1;
        end
    `endif
endmodule

GP01/iir_filter/tb/dump.vcd
$date
	Mon Sep 16 23:26:13 2024
$end
$version
	Icarus Verilog
$end
$timescale
	1ps
$end
$scope module iir_filter $end
$var wire 1 ! i_clock $end
$var wire 8 " i_data [7:0] $end
$var wire 1 # i_reset $end
$var wire 12 $ o_data [11:0] $end
$var wire 24 % y_samples_divided [23:0] $end
$var wire 12 & pipe_result [11:0] $end
$var wire 24 ' partial_sums_y [23:0] $end
$var wire 36 ( partial_sums_x [35:0] $end
$var wire 12 ) ed_result [11:0] $end
$var parameter 32 * ADD_OUTPUT_PIPE $end
$var parameter 32 + NB_DATA_IN $end
$var parameter 32 , NB_DATA_OUT $end
$var parameter 32 - N_INPUT_SAMPLES $end
$var parameter 32 . N_OUTPUT_SAMPLES $end
$var reg 24 / x_samples [23:0] $end
$var reg 24 0 y_samples [23:0] $end
$scope begin gen_assigns_divisions[0] $end
$var parameter 2 1 g_sample $end
$upscope $end
$scope begin gen_assigns_divisions[1] $end
$var parameter 2 2 g_sample $end
$upscope $end
$scope begin gen_direct_out $end
$upscope $end
$scope begin gen_xi_partial_sums[1] $end
$var parameter 2 3 g_sum_xi $end
$upscope $end
$scope begin gen_xi_partial_sums[2] $end
$var parameter 3 4 g_sum_xi $end
$upscope $end
$scope begin gen_yi_partial_sums[1] $end
$var parameter 2 5 g_sum_yi $end
$upscope $end
$scope begin proc_filtering $end
$upscope $end
$upscope $end
$enddefinitions $end
$comment Show the parameter values. $end
$dumpall
b1 5
b10 4
b1 3
b1 2
b0 1
b10 .
b11 -
b1100 ,
b1000 +
b0 *
$end
#0
$dumpvars
bx 0
bx00000000 /
bx )
bx000000000000 (
bx '
bx &
bx %
bx $
0#
b0 "
1!
$end
#5000
0!
#10000
1#
bx000000000000000000000000 (
bx0000000000000000 /
1!
#15000
0!
#20000
b0 $
b0 &
b0 )
b0 '
b0 %
b0 (
b0 0
b0 /
1!
#25000
0!
#30000
0#
1!
#35000
0!
#40000
b11 $
b11 &
b11 )
b11000000000011000000000011 (
b11 "
1!
#45000
0!
#50000
b1 $
b1 &
b1 )
b1000000000001 '
b1 %
b0 (
b11 0
b11 /
1!
#55000
0!
#60000
b0 '
b11 $
b11 &
b11 )
b0 %
b11000000000011000000000000 (
b1000000000001 0
b1100000011 /
1!
#65000
0!
#70000
b1000000000001 '
b1 %
b111 $
b111 &
b111 )
b110000000000011000000000000 (
b11 0
b110000001100000011 /
1!
#75000
0!
#80000
b1001 $
b1001 &
b1001 )
b11000000000011 '
b11 %
b1000000000111 0
1!
#85000
0!
#90000
b1011 $
b1011 &
b1011 )
b101000000000100 '
b1000000000100 %
b11000000001001 0
1!
#95000
0!
#100000
b1101 $
b1101 &
b1101 )
b111000000000101 '
b10000000000101 %
b100000000001011 0
1!
#105000
0!
#110000
b1110 $
b1110 &
b1110 )
b1000000000000110 '
b10000000000110 %
b101000000001101 0
1!
#115000
0!
#120000
b10000 $
b10000 &
b10000 )
b1010000000000111 '
b11000000000111 %
b110000000001110 0
1!
#125000
0!
#130000
b10001 $
b10001 &
b10001 )
b1011000000001000 '
b11000000001000 %
b111000000010000 0
1!
#135000
0!
#140000
b10010 $
b10010 &
b10010 )
b1100000000001000 '
b100000000001000 %
b1000000000010001 0
1!
#145000
0!
#150000
b10011 $
b10011 &
b10011 )
b1101000000001001 '
b100000000001001 %
b1000000000010010 0
1!
#155000
0!
#160000
b1001000000010011 0
1!
