GP01/iir_filter/rtl/iir_filter.sv
module iir_filter
#(
    // * ----------------------------------------------------------------------------------------------
    // * Parameters
    // * ----------------------------------------------------------------------------------------------
    parameter                                                                   NB_DATA_IN       =  8 ,
    parameter                                                                   NB_DATA_OUT      = 18 ,
    parameter                                                                   N_INPUT_SAMPLES  =  3 ,
    parameter                                                                   N_OUTPUT_SAMPLES =  2 ,
    parameter                                                                   ADD_OUTPUT_PIPE  =  0
)
(
    // * ----------------------------------------------------------------------------------------------
    // * Outputs
    // * ----------------------------------------------------------------------------------------------
    output logic signed [ NB_DATA_OUT                                 - 1 : 0 ] o_data                ,

    // * ----------------------------------------------------------------------------------------------
    // * Inputs
    // * ----------------------------------------------------------------------------------------------
    input  logic signed [ NB_DATA_IN                                  - 1 : 0 ] i_data                ,

    // * ----------------------------------------------------------------------------------------------
    // * Clock and reset
    // * ----------------------------------------------------------------------------------------------
    input  logic                                                                i_reset               ,
    input  logic                                                                i_clock
) ;
    // * ----------------------------------------------------------------------------------------------
    // * Localparams
    // * ----------------------------------------------------------------------------------------------
    localparam                                                                  NB_SUM_FORWARD   = 10 ;
    localparam                                                                  NB_FRAC          =  4 ;

    // * ----------------------------------------------------------------------------------------------
    // * Internal logics
    // * ----------------------------------------------------------------------------------------------
    logic  signed       [ N_INPUT_SAMPLES  - 1 : 0 ] [ NB_DATA_IN     - 1 : 0 ] x_samples             ;
    logic  signed       [ N_INPUT_SAMPLES  - 1 : 0 ] [ NB_SUM_FORWARD - 1 : 0 ] partial_sums_x        ;
    logic  signed       [ N_OUTPUT_SAMPLES - 1 : 0 ] [ NB_DATA_OUT    - 1 : 0 ] y_samples             ;
    logic  signed       [ N_OUTPUT_SAMPLES - 1 : 0 ] [ NB_DATA_OUT    - 1 : 0 ] partial_sums_y        ;
    logic  signed       [ N_OUTPUT_SAMPLES - 1 : 0 ] [ NB_DATA_OUT    - 1 : 0 ] y_samples_divided     ;
    logic  signed       [ NB_DATA_OUT                                 - 1 : 0 ] ed_result             ;
    logic  signed       [ NB_DATA_OUT                                 - 1 : 0 ] pipe_result           ;

    // * ----------------------------------------------------------------------------------------------
    // * Output divisions
    // * ----------------------------------------------------------------------------------------------
    generate
        for (genvar g_sample = 0 ; g_sample < N_OUTPUT_SAMPLES ; g_sample++)
        begin : gen_assigns_divisions
            assign y_samples_divided[g_sample] = y_samples[g_sample] >>> 1;
        end
    endgenerate

    // * ----------------------------------------------------------------------------------------------
    // * Result calculation
    // * ----------------------------------------------------------------------------------------------
    assign partial_sums_x[0] = i_data - x_samples[0];
    generate
        for (genvar g_sum_xi = 1 ; g_sum_xi < N_INPUT_SAMPLES ; g_sum_xi++)
        begin : gen_xi_partial_sums
            assign partial_sums_x[g_sum_xi] = partial_sums_x[g_sum_xi-1] + x_samples[g_sum_xi];
        end
    endgenerate

    assign partial_sums_y[0] = y_samples_divided[0];
    generate
        for (genvar g_sum_yi = 1 ; g_sum_yi < N_OUTPUT_SAMPLES ; g_sum_yi++)
        begin : gen_yi_partial_sums
            assign partial_sums_y[g_sum_yi] = partial_sums_y[g_sum_yi-1] + y_samples_divided[g_sum_yi];
        end
    endgenerate

    assign ed_result = {partial_sums_x[N_INPUT_SAMPLES-1], {NB_FRAC{1'b0}}} + partial_sums_y[N_OUTPUT_SAMPLES-1];

    // * ----------------------------------------------------------------------------------------------
    // * Sampling
    // * ----------------------------------------------------------------------------------------------
    always_ff @(posedge i_clock)
    begin : proc_filtering
        if (i_reset) begin
            x_samples <= '0;
            y_samples <= '0;
        end else begin
            x_samples <= {x_samples        [N_INPUT_SAMPLES -2:0], i_data   };
            y_samples <= {y_samples_divided[N_OUTPUT_SAMPLES-2:0], ed_result};
        end
    end

    // * ----------------------------------------------------------------------------------------------
    // * Optional pipe out
    // * ----------------------------------------------------------------------------------------------
    if (ADD_OUTPUT_PIPE)
    begin : gen_pipe_out
        always_ff @(i_clock)
        begin : proc_pipe_out
            pipe_result <= ed_result;
        end
    end else
    begin : gen_direct_out
        assign pipe_result = ed_result;
    end

    // * ----------------------------------------------------------------------------------------------
    // * Output assignment
    // * ----------------------------------------------------------------------------------------------
    assign o_data = pipe_result;

    // * ----------------------------------------------------------------------------------------------
    // * Simulation define
    // * ----------------------------------------------------------------------------------------------
    `ifdef COCOTB_SIM
        initial begin
            $dumpfile ("dump.vcd");
            $dumpvars ();
            #1;
        end
    `endif
endmodule

GP01/iir_filter/tb/dump.vcd
$date
	Mon Oct  7 18:13:51 2024
$end
$version
	Icarus Verilog
$end
$timescale
	1ps
$end
$scope module iir_filter $end
$var wire 1 ! i_clock $end
$var wire 8 " i_data [7:0] $end
$var wire 1 # i_reset $end
$var wire 18 $ o_data [17:0] $end
$var wire 36 % y_samples_divided [35:0] $end
$var wire 18 & pipe_result [17:0] $end
$var wire 36 ' partial_sums_y [35:0] $end
$var wire 30 ( partial_sums_x [29:0] $end
$var wire 18 ) ed_result [17:0] $end
$var parameter 32 * ADD_OUTPUT_PIPE $end
$var parameter 32 + NB_DATA_IN $end
$var parameter 32 , NB_DATA_OUT $end
$var parameter 32 - NB_FRAC $end
$var parameter 32 . NB_SUM_FORWARD $end
$var parameter 32 / N_INPUT_SAMPLES $end
$var parameter 32 0 N_OUTPUT_SAMPLES $end
$var reg 24 1 x_samples [23:0] $end
$var reg 36 2 y_samples [35:0] $end
$scope begin gen_assigns_divisions[0] $end
$var parameter 2 3 g_sample $end
$upscope $end
$scope begin gen_assigns_divisions[1] $end
$var parameter 2 4 g_sample $end
$upscope $end
$scope begin gen_direct_out $end
$upscope $end
$scope begin gen_xi_partial_sums[1] $end
$var parameter 2 5 g_sum_xi $end
$upscope $end
$scope begin gen_xi_partial_sums[2] $end
$var parameter 3 6 g_sum_xi $end
$upscope $end
$scope begin gen_yi_partial_sums[1] $end
$var parameter 2 7 g_sum_yi $end
$upscope $end
$scope begin proc_filtering $end
$upscope $end
$upscope $end
$enddefinitions $end
$comment Show the parameter values. $end
$dumpall
b1 7
b10 6
b1 5
b1 4
b0 3
b10 0
b11 /
b1010 .
b100 -
b10010 ,
b1000 +
b0 *
$end
#0
$dumpvars
bx 2
bx00000000 1
bx )
bx0000000000 (
bx '
bx &
bx %
bx $
0#
b0 "
1!
$end
#5000
0!
#10000
1#
bx00000000000000000000 (
bx0000000000000000 1
1!
#15000
0!
#20000
b0 $
b0 &
b0 )
b0 '
b0 %
b0 (
b0 2
b0 1
1!
#25000
0!
#30000
0#
1!
#35000
0!
#40000
b11100000000000 $
b11100000000000 &
b11100000000000 )
b111000000011100000001110000000 (
b10000000 "
1!
#45000
0!
#50000
b1110000000000 $
b1110000000000 &
b1110000000000 )
b1110000000000000001110000000000 '
b1110000000000 %
b0 (
b11100000000000 2
b10000000 1
1!
#50001
b10010000000000 $
b10010000000000 &
b10010000000000 )
b1000000000100000000010000000 (
b0 "
#55001
0!
#60001
b10000000000000000001001000000000 '
b101100000000000 $
b101100000000000 &
b101100000000000 )
b111000000000000001001000000000 %
b111000000011100000000000000000 (
b1110000000000000010010000000000 2
b1000000000000000 1
1!
#65001
0!
#70001
1#
b11010100000000000010110000000000 '
b100100000000000010110000000000 %
b110110100000000 $
b110110100000000 &
b110110100000000 )
b111000000000000000000000000000 (
b1001000000000000101100000000000 2
b100000000000000000000000 1
1!
#75001
0!
#80001
b0 '
b0 %
b0 $
b0 &
b0 )
b0 (
b0 2
b0 1
1!
#85001
0!
#90001
0#
1!
#95001
0!
#100001
1!
#105001
0!
#110001
1!
#115001
0!
#120001
1!
#125001
0!
#130001
1!
#135001
0!
#140001
1!
#145001
0!
#150001
1!
#155001
0!
#160001
1!
#165001
0!
#170001
1!
#175001
0!
#180001
1!
#185001
0!
#190001
1!
#195001
0!
#200001
1!
#205001
0!
#210001
1!
#215001
0!
#220001
1!
#225001
0!
#230001
b11110011010000 $
b11110011010000 &
b11110011010000 )
b111100110111110011011111001101 (
b11001101 "
1!
#235001
0!
#240001
b1111001101000 $
b1111001101000 &
b1111001101000 )
b1111001101000000001111001101000 '
b1111001101000 %
b0 (
b11110011010000 2
b11001101 1
1!
#240002
b10000110011000 $
b10000110011000 &
b10000110011000 )
b11001100001100110000110011 (
b0 "
#245002
0!
#250002
b10000000000000000001000011001100 '
b101110011010000 $
b101110011010000 &
b101110011010000 )
b111100110100000001000011001100 %
b111100110111110011010000000000 (
b1111001101000000010000110011000 2
b1100110100000000 1
1!
#255002
0!
#260002
1#
b11011011001110000010111001101000 '
b100001100110000010111001101000 %
b111001110011110 $
b111001110011110 &
b111001110011110 )
b111100110100000000000000000000 (
b1000011001100000101110011010000 2
b110011010000000000000000 1
1!
#265002
0!
#270002
b0 '
b0 %
b0 $
b0 &
b0 )
b0 (
b0 2
b0 1
1!
#275002
0!
#280002
0#
1!
#285002
0!
#290002
1!
#295002
0!
#300002
1!
#305002
0!
#310002
1!
#315002
0!
#320002
1!
#325002
0!
#330002
1!
#335002
0!
#340002
1!
#345002
0!
#350002
1!
#355002
0!
#360002
1!
#365002
0!
#370002
1!
#375002
0!
#380002
1!
#385002
0!
#390002
1!
#395002
0!
#400002
1!
#405002
0!
#410002
1!
#415002
0!
#420002
1!
#425002
0!
#430002
1!
#435002
0!
#440002
1!
#445002
0!
#450002
1!
#455002
0!
#460002
b10000 $
b10000 &
b10000 )
b100000000010000000001 (
b1 "
1!
#465002
0!
#470002
b1000 $
b1000 &
b1000 )
b1000000000000000001000 '
b1000 %
b0 (
b10000 2
b1 1
1!
#475002
0!
#480002
b1000000000000000000100 '
b11000 $
b11000 &
b11000 )
b100000000000000000100 %
b100000000010000000000 (
b1000000000000000001000 2
b100000001 1
1!
#480003
b1000 $
b1000 &
b1000 )
b1111111111 (
b0 "
#485003
0!
#490003
b110000000000000000100 '
b10000000000000000100 %
b100110 $
b100110 &
b100110 )
b1000000000010000000000 (
b100000000000000001000 2
b10000000100000000 1
1!
#495003
0!
#500003
1#
b10101000000000000010011 '
b100101 $
b100101 &
b100101 )
b10000000000000010011 %
b100000000000000000000 (
b100000000000000100110 2
b10000000000000000 1
1!
#505003
0!
#510003
b0 '
b0 %
b0 $
b0 &
b0 )
b0 (
b0 2
b0 1
1!
#515003
0!
#520003
0#
1!
#525003
0!
#530003
1!
#535003
0!
#540003
1!
#545003
0!
#550003
b10000 $
b10000 &
b10000 )
b100000000010000000001 (
b1 "
1!
#555003
0!
#560003
b10 "
b11000 $
b11000 &
b11000 )
b1000000000000000001000 '
b1000 %
b100000000010000000001 (
b10000 2
b1 1
1!
#565003
0!
#570003
b100000 $
b100000 &
b100000 )
b10000000000000000001100 '
b100000000000000001100 %
b100000000010000000000 (
b1000000000000000011000 2
b100000010 1
1!
#570004
b100000000000000 $
b100000000000000 &
b100000000000000 )
b111111111111111111111111111110 (
b0 "
#575004
0!
#580004
b10000000000110000010000000000000 '
b110000010000000000000 %
b10000000110110 $
b10000000110110 &
b10000000110110 )
b1100000000100000000000 (
b1100000100000000000000 2
b10000001000000000 1
1!
#585004
0!
#590004
1#
b10000000011011000001000000011011 '
b1000000000000000001000000011011 %
b10000000111011 $
b10000000111011 &
b10000000111011 )
b1000000000000000000000 (
b10000000000000000010000000110110 2
b100000000000000000 1
1!
#595004
0!
#600004
b0 '
b0 %
b0 $
b0 &
b0 )
b0 (
b0 2
b0 1
1!
#605004
0!
#610004
0#
1!
#615004
0!
#620004
1!
#625004
0!
#630004
1!
#635004
0!
#640004
b10110000 $
b10110000 &
b10110000 )
b101100000010110000001011 (
b1011 "
1!
#645004
0!
#650004
b10011 "
b11011000 $
b11011000 &
b11011000 )
b1011000000000000001011000 '
b1011000 %
b100000000010000000001000 (
b10110000 2
b1011 1
1!
#655004
0!
#660004
b10011000000000000001101100 '
b101001000 $
b101001000 &
b101001000 )
b101100000000000001101100 %
b101100000010110000000000 (
b1011000000000000011011000 2
b101100010011 1
1!
#660005
b100000000011000 $
b100000000011000 &
b100000000011000 )
b111111100011111110001111101101 (
b0 "
#665005
0!
#670005
b10000001000010000010000000001100 '
b110110000010000000001100 %
b10001000100010 $
b10001000100010 &
b10001000100010 )
b1111000000100110000000000 (
b1101100000100000000011000 2
b10110001001100000000 1
1!
#675005
0!
#680005
1#
b10000100010111000001000100010001 '
b1000000000110000001000100010001 %
b10001001000111 $
b10001001000111 &
b10001001000111 )
b1001100000000000000000000 (
b10000000001100000010001000100010 2
b100110000000000000000 1
1!
#685005
0!
#690005
b0 '
b0 %
b0 $
b0 &
b0 )
b0 (
b0 2
b0 1
1!
#695005
0!
#700005
0#
1!
#705005
0!
#710005
1!
#715005
0!
#720005
b101000000 $
b101000000 &
b101000000 )
b1010000000101000000010100 (
b10100 "
1!
#725005
0!
#730005
b10100000 $
b10100000 &
b10100000 )
b10100000000000000010100000 '
b10100000 %
b0 (
b101000000 2
b10100 1
1!
#735005
0!
#740005
b10100000000000000001010000 '
b111100000 $
b111100000 &
b111100000 )
b1010000000000000001010000 %
b1010000000101000000000000 (
b10100000000000000010100000 2
b1010000010100 1
1!
